{"fixtures":[],"history":[{"element":112,"fixture":2,"opponent_team":4,"total_points":2,"was_home":true,"kickoff_time":"2021-08-14T14:00:00Z","team_h_score":1,"team_a_score":2,"round":1,"minutes":90,"goals_scored":0,"assists":0,"clean_sheets":0,"goals_conceded":2,"own_goals":0,"penalties_saved":0,"penalties_missed":0,"yellow_cards":0,"red_cards":0,"saves":4,"bonus":0,"bps":17,"influence":"30.0","creativity":"0.0","threat":"0.0","ict_index":"3.0","value":55,"transfers_balance":0,"selected":280784,"transfers_in":0,"transfers_out":0},{"element":112,"fixture":15,"opponent_team":11,"total_points":3,"was_home":false,"kickoff_time":"2021-08-21T11:30:00Z","team_h_score":2,"team_a_score":0,"round":2,"minutes":90,"goals_scored":0,"assists":0,"clean_sheets":0,"goals_conceded":2,"own_goals":0,"penalties_saved":0,"penalties_missed":0,"yellow_cards":0,"red_cards":0,"saves":6,"bonus":0,"bps":23,"influence":"48.8","creativity":"0.0","threat":"0.0","ict_index":"4.9","value":55,"transfers_balance":-26086,"selected":275954,"transfers_in":3274,"transfers_out":29360},{"element":112,"fixture":29,"opponent_team":10,"total_points":2,"was_home":true,"kickoff_time":"2021-08-29T13:00:00Z","team_h_score":1,"team_a_score":1,"round":3,"minutes":90,"goals_scored":0,"assists":0,"clean_sheets":0,"goals_conceded":1,"own_goals":0,"penalties_saved":0,"penalties_missed":0,"yellow_cards":0,"red_cards":0,"saves":1,"bonus":0,"bps":10,"influence":"11.8","creativity":"0.0","threat":"0.0","ict_index":"1.2","value":55,"transfers_balance":-15950,"selected":267442,"transfers_in":3264,"transfers_out":19214},{"element":112,"fixture":35,"opponent_team":8,"total_points":2,"was_home":false,"kickoff_time":"2021-09-13T19:00:00Z","team_h_score":3,"team_a_score":1,"round":4,"minutes":90,"goals_scored":0,"assists":0,"clean_sheets":0,"goals_conceded":3,"own_goals":0,"penalties_saved":0,"penalties_missed":0,"yellow_cards":0,"red_cards":0,"saves":3,"bonus":0,"bps":14,"influence":"21.6","creativity":"0.0","threat":"0.0","ict_index":"2.2","value":55,"transfers_balance":-15850,"selected":258671,"transfers_in":11012,"transfers_out":26862},{"element":112,"fixture":43,"opponent_team":1,"total_points":2,"was_home":true,"kickoff_time":"2021-09-18T14:00:00Z","team_h_score":0,"team_a_score":1,"round":5,"minutes":90,"goals_scored":0,"assists":0,"clean_sheets":0,"goals_conceded":1,"own_goals":0,"penalties_saved":0,"penalties_missed":0,"yellow_cards":0,"red_cards":0,"saves":2,"bonus":0,"bps":16,"influence":"20.6","creativity":"0.0","threat":"0.0","ict_index":"2.1","value":55,"transfers_balance":-12640,"selected":249623,"transfers_in":6459,"transfers_out":19099},{"element":112,"fixture":57,"opponent_team":9,"total_points":1,"was_home":false,"kickoff_time":"2021-09-25T14:00:00Z","team_h_score":2,"team_a_score":2,"round":6,"minutes":90,"goals_scored":0,"assists":0,"clean_sheets":0,"goals_conceded":2,"own_goals":0,"penalties_saved":0,"penalties_missed":0,"yellow_cards":0,"red_cards":0,"saves":2,"bonus":0,"bps":14,"influence":"15.6","creativity":"0.0","threat":"0.0","ict_index":"1.6","value":54,"transfers_balance":-13916,"selected":237926,"transfers_in":2630,"transfers_out":16546},{"element":112,"fixture":62,"opponent_team":15,"total_points":6,"was_home":true,"kickoff_time":"2021-10-02T14:00:00Z","team_h_score":0,"team_a_score":0,"round":7,"minutes":90,"goals_scored":0,"assists":0,"clean_sheets":1,"goals_conceded":0,"own_goals":0,"penalties_saved":0,"penalties_missed":0,"yellow_cards":0,"red_cards":0,"saves":2,"bonus":0,"bps":27,"influence":"8.0","creativity":"0.0","threat":"0.0","ict_index":"0.8","value":54,"transfers_balance":6512,"selected":251185,"transfers_in":17315,"transfers_out":10803},{"element":112,"fixture":76,"opponent_team":12,"total_points":2,"was_home":false,"kickoff_time":"2021-10-16T14:00:00Z","team_h_score":2,"team_a_score":0,"round":8,"minutes":90,"goals_scored":0,"assists":0,"clean_sheets":0,"goals_conceded":2,"own_goals":0,"penalties_saved":0,"penalties_missed":0,"yellow_cards":0,"red_cards":0,"saves":4,"bonus":0,"bps":18,"influence":"32.4","creativity":"0.0","threat":"0.0","ict_index":"3.2","value":54,"transfers_balance":-15350,"selected":233374,"transfers_in":2774,"transfers_out":18124},{"element":112,"fixture":89,"opponent_team":16,"total_points":1,"was_home":false,"kickoff_time":"2021-10-23T14:00:00Z","team_h_score":2,"team_a_score":2,"round":9,"minutes":90,"goals_scored":0,"assists":0,"clean_sheets":0,"goals_conceded":2,"own_goals":0,"penalties_saved":0,"penalties_missed":0,"yellow_cards":0,"red_cards":0,"saves":2,"bonus":0,"bps":13,"influence":"10.6","creativity":"0.0","threat":"0.0","ict_index":"1.1","value":54,"transfers_balance":-5306,"selected":229503,"transfers_in":2287,"transfers_out":7593},{"element":112,"fixture":92,"opponent_team":3,"total_points":3,"was_home":true,"kickoff_time":"2021-10-30T14:00:00Z","team_h_score":3,"team_a_score":1,"round":10,"minutes":90,"goals_scored":0,"assists":0,"clean_sheets":0,"goals_conceded":1,"own_goals":0,"penalties_saved":0,"penalties_missed":0,"yellow_cards":0,"red_cards":0,"saves":3,"bonus":0,"bps":15,"influence":"15.8","creativity":"0.0","threat":"0.0","ict_index":"1.6","value":54,"transfers_balance":-3522,"selected":227345,"transfers_in":6403,"transfers_out":9925},{"element":112,"fixture":104,"opponent_team":6,"total_points":3,"was_home":false,"kickoff_time":"2021-11-06T15:00:00Z","team_h_score":1,"team_a_score":1,"round":11,"minutes":90,"goals_scored":0,"assists":0,"clean_sheets":0,"goals_conceded":1,"own_goals":0,"penalties_saved":0,"penalties_missed":0,"yellow_cards":0,"red_cards":0,"saves":4,"bonus":0,"bps":17,"influence":"28.4","creativity":"10.0","threat":"0.0","ict_index":"3.8","value":54,"transfers_balance":-7169,"selected":220958,"transfers_in":1948,"transfers_out":9117},{"element":112,"fixture":112,"opponent_team":7,"total_points":2,"was_home":true,"kickoff_time":"2021-11-20T15:00:00Z","team_h_score":3,"team_a_score":3,"round":12,"minutes":90,"goals_scored":0,"assists":0,"clean_sheets":0,"goals_conceded":3,"own_goals":0,"penalties_saved":0,"penalties_missed":0,"yellow_cards":0,"red_cards":0,"saves":5,"bonus":0,"bps":17,"influence":"37.6","creativity":"0.0","threat":"0.0","ict_index":"3.8","value":54,"transfers_balance":645,"selected":223502,"transfers_in":6778,"transfers_out":6133},{"element":112,"fixture":137,"opponent_team":20,"total_points":6,"was_home":false,"kickoff_time":"2021-12-01T19:30:00Z","team_h_score":0,"team_a_score":0,"round":14,"minutes":90,"goals_scored":0,"assists":0,"clean_sheets":1,"goals_conceded":0,"own_goals":0,"penalties_saved":0,"penalties_missed":0,"yellow_cards":0,"red_cards":0,"saves":2,"bonus":0,"bps":24,"influence":"13.8","creativity":"0.0","threat":"0.0","ict_index":"1.4","value":54,"transfers_balance":-2971,"selected":213694,"transfers_in":905,"transfers_out":3876},{"element":112,"fixture":145,"opponent_team":14,"total_points":3,"was_home":false,"kickoff_time":"2021-12-04T15:00:00Z","team_h_score":1,"team_a_score":0,"round":15,"minutes":90,"goals_scored":0,"assists":0,"clean_sheets":0,"goals_conceded":1,"own_goals":0,"penalties_saved":0,"penalties_missed":0,"yellow_cards":0,"red_cards":0,"saves":3,"bonus":0,"bps":12,"influence":"10.8","creativity":"0.0","threat":"0.0","ict_index":"1.1","value":54,"transfers_balance":1225,"selected":215691,"transfers_in":4757,"transfers_out":3532},{"element":112,"fixture":154,"opponent_team":19,"total_points":9,"was_home":true,"kickoff_time":"2021-12-12T14:00:00Z","team_h_score":0,"team_a_score":0,"round":16,"minutes":90,"goals_scored":0,"assists":0,"clean_sheets":1,"goals_conceded":0,"own_goals":0,"penalties_saved":0,"penalties_missed":0,"yellow_cards":0,"red_cards":0,"saves":3,"bonus":2,"bps":27,"influence":"27.4","creativity":"0.0","threat":"0.0","ict_index":"2.7","value":54,"transfers_balance":-5051,"selected":210864,"transfers_in":1645,"transfers_out":6696},{"element":112,"fixture":198,"opponent_team":13,"total_points":0,"was_home":false,"kickoff_time":"2021-12-30T20:15:00Z","team_h_score":3,"team_a_score":1,"round":20,"minutes":0,"goals_scored":0,"assists":0,"clean_sheets":0,"goals_conceded":0,"own_goals":0,"penalties_saved":0,"penalties_missed":0,"yellow_cards":0,"red_cards":0,"saves":0,"bonus":0,"bps":0,"influence":"0.0","creativity":"0.0","threat":"0.0","ict_index":"0.0","value":54,"transfers_balance":1398,"selected":211693,"transfers_in":4157,"transfers_out":2759},{"element":112,"fixture":206,"opponent_team":10,"total_points":0,"was_home":false,"kickoff_time":"2022-01-02T14:00:00Z","team_h_score":3,"team_a_score":1,"round":21,"minutes":0,"goals_scored":0,"assists":0,"clean_sheets":0,"goals_conceded":0,"own_goals":0,"penalties_saved":0,"penalties_missed":0,"yellow_cards":0,"red_cards":0,"saves":0,"bonus":0,"bps":0,"influence":"0.0","creativity":"0.0","threat":"0.0","ict_index":"0.0","value":54,"transfers_balance":-6553,"selected":202526,"transfers_in":1290,"transfers_out":7843},{"element":112,"fixture":221,"opponent_team":1,"total_points":10,"was_home":false,"kickoff_time":"2022-01-23T14:00:00Z","team_h_score":0,"team_a_score":0,"round":23,"minutes":90,"goals_scored":0,"assists":0,"clean_sheets":1,"goals_conceded":0,"own_goals":0,"penalties_saved":0,"penalties_missed":0,"yellow_cards":0,"red_cards":0,"saves":5,"bonus":3,"bps":31,"influence":"35.0","creativity":"0.0","threat":"0.0","ict_index":"3.5","value":54,"transfers_balance":1767,"selected":203078,"transfers_in":5142,"transfers_out":3375},{"element":112,"fixture":164,"opponent_team":18,"total_points":9,"was_home":true,"kickoff_time":"2022-02-05T18:00:00Z","team_h_score":0,"team_a_score":0,"round":23,"minutes":90,"goals_scored":0,"assists":0,"clean_sheets":1,"goals_conceded":0,"own_goals":0,"penalties_saved":0,"penalties_missed":0,"yellow_cards":0,"red_cards":0,"saves":5,"bonus":2,"bps":31,"influence":"38.8","creativity":"0.0","threat":"0.0","ict_index":"3.9","value":54,"transfers_balance":1767,"selected":203078,"transfers_in":5142,"transfers_out":3375},{"element":112,"fixture":233,"opponent_team":13,"total_points":3,"was_home":true,"kickoff_time":"2022-02-08T20:00:00Z","team_h_score":1,"team_a_score":1,"round":24,"minutes":90,"goals_scored":0,"assists":0,"clean_sheets":0,"goals_conceded":1,"own_goals":0,"penalties_saved":0,"penalties_missed":0,"yellow_cards":0,"red_cards":0,"saves":4,"bonus":0,"bps":17,"influence":"34.6","creativity":"0.0","threat":"0.0","ict_index":"3.5","value":54,"transfers_balance":4722,"selected":209017,"transfers_in":9193,"transfers_out":4471},{"element":112,"fixture":242,"opponent_team":11,"total_points":3,"was_home":true,"kickoff_time":"2022-02-13T14:00:00Z","team_h_score":0,"team_a_score":1,"round":25,"minutes":90,"goals_scored":0,"assists":0,"clean_sheets":0,"goals_conceded":1,"own_goals":0,"penalties_saved":0,"penalties_missed":0,"yellow_cards":0,"red_cards":0,"saves":3,"bonus":0,"bps":15,"influence":"23.2","creativity":"0.0","threat":"0.0","ict_index":"2.3","value":54,"transfers_balance":5056,"selected":214427,"transfers_in":10823,"transfers_out":5767},{"element":112,"fixture":253,"opponent_team":4,"total_points":7,"was_home":false,"kickoff_time":"2022-02-19T15:00:00Z","team_h_score":0,"team_a_score":3,"round":26,"minutes":90,"goals_scored":0,"assists":0,"clean_sheets":1,"goals_conceded":0,"own_goals":0,"penalties_saved":0,"penalties_missed":0,"yellow_cards":0,"red_cards":0,"saves":1,"bonus":1,"bps":25,"influence":"8.0","creativity":"10.0","threat":"0.0","ict_index":"1.8","value":54,"transfers_balance":43456,"selected":289308,"transfers_in":50711,"transfers_out":7255},{"element":112,"fixture":124,"opponent_team":17,"total_points":6,"was_home":true,"kickoff_time":"2022-02-23T19:30:00Z","team_h_score":1,"team_a_score":0,"round":26,"minutes":90,"goals_scored":0,"assists":0,"clean_sheets":1,"goals_conceded":0,"own_goals":0,"penalties_saved":0,"penalties_missed":0,"yellow_cards":0,"red_cards":0,"saves":2,"bonus":0,"bps":23,"influence":"18.2","creativity":"0.0","threat":"0.0","ict_index":"1.8","value":54,"transfers_balance":43456,"selected":289308,"transfers_in":50711,"transfers_out":7255},{"element":112,"fixture":265,"opponent_team":7,"total_points":3,"was_home":false,"kickoff_time":"2022-02-26T15:00:00Z","team_h_score":1,"team_a_score":1,"round":27,"minutes":90,"goals_scored":0,"assists":0,"clean_sheets":0,"goals_conceded":1,"own_goals":0,"penalties_saved":0,"penalties_missed":0,"yellow_cards":0,"red_cards":0,"saves":3,"bonus":0,"bps":16,"influence":"22.8","creativity":"0.0","threat":"0.0","ict_index":"2.3","value":54,"transfers_balance":105427,"selected":676431,"transfers_in":111782,"transfers_out":6355},{"element":112,"fixture":213,"opponent_team":9,"total_points":2,"was_home":true,"kickoff_time":"2022-03-01T19:45:00Z","team_h_score":0,"team_a_score":2,"round":27,"minutes":90,"goals_scored":0,"assists":0,"clean_sheets":0,"goals_conceded":2,"own_goals":0,"penalties_saved":0,"penalties_missed":0,"yellow_cards":0,"red_cards":0,"saves":4,"bonus":0,"bps":16,"influence":"35.4","creativity":"0.0","threat":"0.0","ict_index":"3.5","value":54,"transfers_balance":105427,"selected":676431,"transfers_in":111782,"transfers_out":6355},{"element":112,"fixture":272,"opponent_team":6,"total_points":0,"was_home":true,"kickoff_time":"2022-03-05T15:00:00Z","team_h_score":0,"team_a_score":4,"round":28,"minutes":90,"goals_scored":0,"assists":0,"clean_sheets":0,"goals_conceded":4,"own_goals":0,"penalties_saved":0,"penalties_missed":0,"yellow_cards":0,"red_cards":0,"saves":1,"bonus":0,"bps":10,"influence":"5.0","creativity":"0.0","threat":"0.0","ict_index":"0.5","value":54,"transfers_balance":-55746,"selected":299255,"transfers_in":5813,"transfers_out":61559},{"element":112,"fixture":282,"opponent_team":3,"total_points":1,"was_home":false,"kickoff_time":"2022-03-12T15:00:00Z","team_h_score":2,"team_a_score":0,"round":29,"minutes":90,"goals_scored":0,"assists":0,"clean_sheets":0,"goals_conceded":2,"own_goals":0,"penalties_saved":0,"penalties_missed":0,"yellow_cards":0,"red_cards":0,"saves":1,"bonus":0,"bps":12,"influence":"6.0","creativity":"0.0","threat":"0.0","ict_index":"0.6","value":54,"transfers_balance":-19958,"selected":286522,"transfers_in":3599,"transfers_out":23557},{"element":112,"fixture":302,"opponent_team":12,"total_points":2,"was_home":true,"kickoff_time":"2022-04-02T14:00:00Z","team_h_score":0,"team_a_score":2,"round":31,"minutes":90,"goals_scored":0,"assists":0,"clean_sheets":0,"goals_conceded":2,"own_goals":0,"penalties_saved":0,"penalties_missed":0,"yellow_cards":0,"red_cards":0,"saves":4,"bonus":0,"bps":18,"influence":"26.8","creativity":"0.0","threat":"0.0","ict_index":"2.7","value":54,"transfers_balance":90305,"selected":372069,"transfers_in":98489,"transfers_out":8184},{"element":112,"fixture":183,"opponent_team":8,"total_points":1,"was_home":true,"kickoff_time":"2022-04-06T18:30:00Z","team_h_score":3,"team_a_score":2,"round":31,"minutes":90,"goals_scored":0,"assists":0,"clean_sheets":0,"goals_conceded":2,"own_goals":0,"penalties_saved":0,"penalties_missed":0,"yellow_cards":0,"red_cards":0,"saves":2,"bonus":0,"bps":13,"influence":"14.6","creativity":"0.0","threat":"0.0","ict_index":"1.5","value":54,"transfers_balance":90305,"selected":372069,"transfers_in":98489,"transfers_out":8184},{"element":112,"fixture":318,"opponent_team":15,"total_points":2,"was_home":false,"kickoff_time":"2022-04-10T13:00:00Z","team_h_score":2,"team_a_score":0,"round":32,"minutes":90,"goals_scored":0,"assists":0,"clean_sheets":0,"goals_conceded":2,"own_goals":0,"penalties_saved":0,"penalties_missed":0,"yellow_cards":0,"red_cards":0,"saves":4,"bonus":0,"bps":17,"influence":"32.4","creativity":"0.0","threat":"0.0","ict_index":"3.2","value":54,"transfers_balance":3981,"selected":375007,"transfers_in":13447,"transfers_out":9466},{"element":112,"fixture":329,"opponent_team":19,"total_points":3,"was_home":false,"kickoff_time":"2022-04-17T13:15:00Z","team_h_score":1,"team_a_score":1,"round":33,"minutes":90,"goals_scored":0,"assists":0,"clean_sheets":0,"goals_conceded":1,"own_goals":0,"penalties_saved":0,"penalties_missed":0,"yellow_cards":0,"red_cards":0,"saves":5,"bonus":0,"bps":21,"influence":"45.4","creativity":"0.0","threat":"0.0","ict_index":"4.5","value":54,"transfers_balance":-4636,"selected":369543,"transfers_in":10883,"transfers_out":15519},{"element":112,"fixture":292,"opponent_team":16,"total_points":7,"was_home":true,"kickoff_time":"2022-04-21T18:45:00Z","team_h_score":2,"team_a_score":0,"round":33,"minutes":90,"goals_scored":0,"assists":0,"clean_sheets":1,"goals_conceded":0,"own_goals":0,"penalties_saved":0,"penalties_missed":0,"yellow_cards":0,"red_cards":0,"saves":3,"bonus":0,"bps":30,"influence":"25.4","creativity":"0.0","threat":"0.0","ict_index":"2.5","value":54,"transfers_balance":-4636,"selected":369543,"transfers_in":10883,"transfers_out":15519},{"element":112,"fixture":334,"opponent_team":20,"total_points":10,"was_home":true,"kickoff_time":"2022-04-24T13:00:00Z","team_h_score":1,"team_a_score":0,"round":34,"minutes":90,"goals_scored":0,"assists":0,"clean_sheets":1,"goals_conceded":0,"own_goals":0,"penalties_saved":0,"penalties_missed":0,"yellow_cards":0,"red_cards":0,"saves":4,"bonus":3,"bps":30,"influence":"30.8","creativity":"0.0","threat":"0.0","ict_index":"3.1","value":54,"transfers_balance":-17924,"selected":351190,"transfers_in":3346,"transfers_out":21270},{"element":112,"fixture":348,"opponent_team":18,"total_points":2,"was_home":false,"kickoff_time":"2022-04-30T14:00:00Z","team_h_score":1,"team_a_score":2,"round":35,"minutes":90,"goals_scored":0,"assists":0,"clean_sheets":0,"goals_conceded":1,"own_goals":0,"penalties_saved":0,"penalties_missed":0,"yellow_cards":0,"red_cards":0,"saves":1,"bonus":0,"bps":13,"influence":"14.2","creativity":"0.0","threat":"0.0","ict_index":"1.4","value":54,"transfers_balance":2215,"selected":356381,"transfers_in":13310,"transfers_out":11095},{"element":112,"fixture":354,"opponent_team":2,"total_points":2,"was_home":true,"kickoff_time":"2022-05-07T14:00:00Z","team_h_score":1,"team_a_score":3,"round":36,"minutes":90,"goals_scored":0,"assists":0,"clean_sheets":0,"goals_conceded":3,"own_goals":0,"penalties_saved":0,"penalties_missed":0,"yellow_cards":0,"red_cards":0,"saves":4,"bonus":0,"bps":18,"influence":"30.0","creativity":"0.0","threat":"0.0","ict_index":"3.0","value":53,"transfers_balance":-39775,"selected":307737,"transfers_in":4888,"transfers_out":44663},{"element":112,"fixture":367,"opponent_team":17,"total_points":3,"was_home":false,"kickoff_time":"2022-05-15T11:00:00Z","team_h_score":1,"team_a_score":0,"round":37,"minutes":90,"goals_scored":0,"assists":0,"clean_sheets":0,"goals_conceded":1,"own_goals":0,"penalties_saved":0,"penalties_missed":0,"yellow_cards":1,"red_cards":0,"saves":6,"bonus":0,"bps":20,"influence":"45.0","creativity":"0.0","threat":"0.0","ict_index":"4.5","value":53,"transfers_balance":-235,"selected":320557,"transfers_in":10433,"transfers_out":10668},{"element":112,"fixture":171,"opponent_team":2,"total_points":5,"was_home":false,"kickoff_time":"2022-05-19T19:00:00Z","team_h_score":1,"team_a_score":1,"round":37,"minutes":90,"goals_scored":0,"assists":0,"clean_sheets":0,"goals_conceded":1,"own_goals":0,"penalties_saved":0,"penalties_missed":0,"yellow_cards":0,"red_cards":0,"saves":8,"bonus":1,"bps":26,"influence":"50.8","creativity":"0.0","threat":"0.0","ict_index":"5.1","value":53,"transfers_balance":-235,"selected":320557,"transfers_in":10433,"transfers_out":10668},{"element":112,"fixture":374,"opponent_team":14,"total_points":2,"was_home":true,"kickoff_time":"2022-05-22T15:00:00Z","team_h_score":1,"team_a_score":2,"round":38,"minutes":90,"goals_scored":0,"assists":0,"clean_sheets":0,"goals_conceded":2,"own_goals":0,"penalties_saved":0,"penalties_missed":0,"yellow_cards":0,"red_cards":0,"saves":4,"bonus":0,"bps":17,"influence":"0.0","creativity":"0.0","threat":"0.0","ict_index":"0.0","value":53,"transfers_balance":5506,"selected":322531,"transfers_in":13423,"transfers_out":7917}],"history_past":[{"season_name":"2016/17","element_code":98747,"start_cost":40,"end_cost":39,"total_points":0,"minutes":0,"goals_scored":0,"assists":0,"clean_sheets":0,"goals_conceded":0,"own_goals":0,"penalties_saved":0,"penalties_missed":0,"yellow_cards":0,"red_cards":0,"saves":0,"bonus":0,"bps":0,"influence":"0.0","creativity":"0.0","threat":"0.0","ict_index":"0.0"},{"season_name":"2017/18","element_code":98747,"start_cost":45,"end_cost":50,"total_points":152,"minutes":3114,"goals_scored":0,"assists":0,"clean_sheets":11,"goals_conceded":35,"own_goals":0,"penalties_saved":1,"penalties_missed":0,"yellow_cards":3,"red_cards":0,"saves":113,"bonus":19,"bps":701,"influence":"862.4","creativity":"40.0","threat":"0.0","ict_index":"90.1"},{"season_name":"2018/19","element_code":98747,"start_cost":50,"end_cost":48,"total_points":0,"minutes":0,"goals_scored":0,"assists":0,"clean_sheets":0,"goals_conceded":0,"own_goals":0,"penalties_saved":0,"penalties_missed":0,"yellow_cards":0,"red_cards":0,"saves":0,"bonus":0,"bps":0,"influence":"0.0","creativity":"0.0","threat":"0.0","ict_index":"0.0"},{"season_name":"2019/20","element_code":98747,"start_cost":45,"end_cost":52,"total_points":170,"minutes":3420,"goals_scored":0,"assists":0,"clean_sheets":15,"goals_conceded":50,"own_goals":0,"penalties_saved":1,"penalties_missed":0,"yellow_cards":1,"red_cards":0,"saves":120,"bonus":23,"bps":789,"influence":"900.0","creativity":"30.3","threat":"2.0","ict_index":"93.1"},{"season_name":"2020/21","element_code":98747,"start_cost":55,"end_cost":55,"total_points":144,"minutes":2880,"goals_scored":0,"assists":0,"clean_sheets":11,"goals_conceded":37,"own_goals":0,"penalties_saved":0,"penalties_missed":0,"yellow_cards":1,"red_cards":0,"saves":114,"bonus":20,"bps":652,"influence":"846.6","creativity":"20.0","threat":"2.0","ict_index":"86.8"}]}