[{"code":2562036,"event":15,"finished":true,"finished_provisional":true,"id":141,"kickoff_time":"2025-12-06T12:30:00Z","minutes":90,"provisional_start_time":false,"started":true,"team_a":1,"team_a_score":1,"team_h":2,"team_h_score":2,"stats":[{"identifier":"goals_scored","a":[{"value":1,"element":20}],"h":[{"value":1,"element":36},{"value":1,"element":50}]},{"identifier":"assists","a":[{"value":1,"element":16}],"h":[{"value":1,"element":41},{"value":1,"element":58}]},{"identifier":"own_goals","a":[],"h":[]},{"identifier":"penalties_saved","a":[],"h":[]},{"identifier":"penalties_missed","a":[],"h":[]},{"identifier":"yellow_cards","a":[{"value":1,"element":7},{"value":1,"element":16}],"h":[]},{"identifier":"red_cards","a":[],"h":[]},{"identifier":"saves","a":[{"value":4,"element":1}],"h":[{"value":7,"element":32}]},{"identifier":"bonus","a":[{"value":2,"element":21}],"h":[{"value":3,"element":58},{"value":1,"element":36}]},{"identifier":"bps","a":[{"value":30,"element":21},{"value":23,"element":20},{"value":21,"element":17},{"value":18,"element":11},{"value":18,"element":16},{"value":14,"element":26},{"value":13,"element":1},{"value":11,"element":725},{"value":7,"element":8},{"value":4,"element":22},{"value":4,"element":266},{"value":3,"element":18},{"value":3,"element":666},{"value":2,"element":7},{"value":2,"element":19},{"value":-1,"element":10}],"h":[{"value":37,"element":58},{"value":24,"element":36},{"value":22,"element":50},{"value":21,"element":32},{"value":17,"element":41},{"value":13,"element":48},{"value":12,"element":47},{"value":11,"element":38},{"value":11,"element":54},{"value":9,"element":456},{"value":8,"element":64},{"value":7,"element":39},{"value":5,"element":59},{"value":3,"element":44},{"value":3,"element":719},{"value":-3,"element":53}]},{"identifier":"defensive_contribution","a":[{"value":21,"element":21},{"value":13,"element":725},{"value":10,"element":8},{"value":10,"element":17},{"value":8,"element":26},{"value":7,"element":16},{"value":6,"element":7},{"value":5,"element":11},{"value":5,"element":22},{"value":2,"element":20},{"value":2,"element":666}],"h":[{"value":12,"element":58},{"value":10,"element":48},{"value":9,"element":59},{"value":7,"element":47},{"value":6,"element":36},{"value":5,"element":38},{"value":5,"element":41},{"value":4,"element":39},{"value":4,"element":54},{"value":4,"element":64},{"value":1,"element":44}]}],"team_h_difficulty":4,"team_a_difficulty":3,"pulse_id":124931},{"code":2562035,"event":15,"finished":true,"finished_provisional":true,"id":142,"kickoff_time":"2025-12-06T15:00:00Z","minutes":90,"provisional_start_time":false,"started":true,"team_a":7,"team_a_score":0,"team_h":4,"team_h_score":0,"stats":[{"identifier":"goals_scored","a":[],"h":[]},{"identifier":"assists","a":[],"h":[]},{"identifier":"own_goals","a":[],"h":[]},{"identifier":"penalties_saved","a":[],"h":[]},{"identifier":"penalties_missed","a":[],"h":[]},{"identifier":"yellow_cards","a":[{"value":1,"element":236},{"value":1,"element":252}],"h":[]},{"identifier":"red_cards","a":[],"h":[]},{"identifier":"saves","a":[{"value":5,"element":220}],"h":[{"value":4,"element":67}]},{"identifier":"bonus","a":[{"value":3,"element":220},{"value":3,"element":226},{"value":1,"element":228},{"value":1,"element":230}],"h":[]},{"identifier":"bps","a":[{"value":35,"element":220},{"value":35,"element":226},{"value":32,"element":228},{"value":32,"element":230},{"value":25,"element":224},{"value":22,"element":225},{"value":15,"element":236},{"value":12,"element":235},{"value":12,"element":237},{"value":8,"element":453},{"value":7,"element":249},{"value":3,"element":250},{"value":2,"element":252}],"h":[{"value":31,"element":67},{"value":31,"element":74},{"value":28,"element":72},{"value":23,"element":73},{"value":22,"element":685},{"value":21,"element":90},{"value":16,"element":713},{"value":15,"element":84},{"value":14,"element":82},{"value":7,"element":81},{"value":4,"element":77},{"value":4,"element":697},{"value":3,"element":86},{"value":1,"element":98},{"value":-3,"element":97}]},{"identifier":"defensive_contribution","a":[{"value":15,"element":230},{"value":11,"element":226},{"value":11,"element":235},{"value":9,"element":225},{"value":6,"element":228},{"value":6,"element":237},{"value":6,"element":249},{"value":4,"element":252},{"value":3,"element":224},{"value":3,"element":236},{"value":3,"element":453}],"h":[{"value":16,"element":84},{"value":16,"element":90},{"value":11,"element":72},{"value":8,"element":74},{"value":6,"element":73},{"value":6,"element":81},{"value":6,"element":685},{"value":5,"element":82},{"value":3,"element":77},{"value":2,"element":697},{"value":1,"element":97},{"value":1,"element":98}]}],"team_h_difficulty":3,"team_a_difficulty":4,"pulse_id":124932},{"code":2562038,"event":15,"finished":true,"finished_provisional":true,"id":144,"kickoff_time":"2025-12-06T15:00:00Z","minutes":90,"provisional_start_time":false,"started":true,"team_a":16,"team_a_score":0,"team_h":9,"team_h_score":3,"stats":[{"identifier":"goals_scored","a":[],"h":[{"value":1,"element":242},{"value":1,"element":310}]},{"identifier":"assists","a":[],"h":[{"value":1,"element":242},{"value":1,"element":293},{"value":1,"element":299}]},{"identifier":"own_goals","a":[{"value":1,"element":505}],"h":[]},{"identifier":"penalties_saved","a":[],"h":[]},{"identifier":"penalties_missed","a":[],"h":[]},{"identifier":"yellow_cards","a":[{"value":1,"element":505},{"value":1,"element":511},{"value":1,"element":716}],"h":[{"value":1,"element":291},{"value":1,"element":292},{"value":1,"element":293},{"value":1,"element":310}]},{"identifier":"red_cards","a":[],"h":[]},{"identifier":"saves","a":[{"value":3,"element":502}],"h":[{"value":2,"element":287}]},{"identifier":"bonus","a":[],"h":[{"value":3,"element":242},{"value":2,"element":291},{"value":1,"element":295}]},{"identifier":"bps","a":[{"value":27,"element":517},{"value":11,"element":526},{"value":10,"element":521},{"value":8,"element":508},{"value":8,"element":669},{"value":7,"element":515},{"value":6,"element":522},{"value":5,"element":513},{"value":3,"element":502},{"value":3,"element":519},{"value":1,"element":693},{"value":-2,"element":511},{"value":-4,"element":505},{"value":-5,"element":716}],"h":[{"value":44,"element":242},{"value":29,"element":291},{"value":28,"element":295},{"value":27,"element":287},{"value":27,"element":292},{"value":27,"element":293},{"value":25,"element":299},{"value":23,"element":310},{"value":19,"element":303},{"value":8,"element":419},{"value":4,"element":300},{"value":4,"element":301},{"value":3,"element":707},{"value":1,"element":311}]},{"identifier":"defensive_contribution","a":[{"value":19,"element":517},{"value":11,"element":505},{"value":11,"element":511},{"value":8,"element":521},{"value":7,"element":513},{"value":6,"element":515},{"value":5,"element":508},{"value":5,"element":519},{"value":5,"element":526},{"value":5,"element":716},{"value":4,"element":669},{"value":4,"element":693},{"value":1,"element":516},{"value":1,"element":522}],"h":[{"value":17,"element":291},{"value":15,"element":242},{"value":14,"element":295},{"value":12,"element":299},{"value":8,"element":292},{"value":7,"element":301},{"value":7,"element":303},{"value":7,"element":419},{"value":6,"element":300},{"value":4,"element":293},{"value":2,"element":310}]}],"team_h_difficulty":2,"team_a_difficulty":3,"pulse_id":124934},{"code":2562041,"event":15,"finished":true,"finished_provisional":true,"id":147,"kickoff_time":"2025-12-06T15:00:00Z","minutes":90,"provisional_start_time":false,"started":true,"team_a":17,"team_a_score":0,"team_h":13,"team_h_score":3,"stats":[{"identifier":"goals_scored","a":[],"h":[{"value":1,"element":403},{"value":1,"element":408},{"value":1,"element":414}]},{"identifier":"assists","a":[],"h":[{"value":2,"element":417},{"value":1,"element":414}]},{"identifier":"own_goals","a":[],"h":[]},{"identifier":"penalties_saved","a":[],"h":[]},{"identifier":"penalties_missed","a":[],"h":[]},{"identifier":"yellow_cards","a":[],"h":[{"value":1,"element":403}]},{"identifier":"red_cards","a":[{"value":1,"element":539}],"h":[]},{"identifier":"saves","a":[{"value":2,"element":670}],"h":[{"value":1,"element":736}]},{"identifier":"bonus","a":[],"h":[{"value":3,"element":417},{"value":2,"element":408},{"value":1,"element":403},{"value":1,"element":414}]},{"identifier":"bps","a":[{"value":16,"element":547},{"value":12,"element":724},{"value":9,"element":552},{"value":7,"element":553},{"value":7,"element":668},{"value":7,"element":735},{"value":3,"element":532},{"value":3,"element":560},{"value":3,"element":670},{"value":3,"element":730},{"value":2,"element":531},{"value":2,"element":543},{"value":1,"element":548},{"value":-2,"element":694},{"value":-3,"element":683},{"value":-7,"element":539}],"h":[{"value":48,"element":417},{"value":44,"element":408},{"value":37,"element":403},{"value":37,"element":414},{"value":36,"element":411},{"value":32,"element":407},{"value":23,"element":418},{"value":22,"element":736},{"value":13,"element":423},{"value":11,"element":416},{"value":5,"element":430},{"value":3,"element":405},{"value":3,"element":410},{"value":2,"element":413},{"value":1,"element":415},{"value":1,"element":427}]},{"identifier":"defensive_contribution","a":[{"value":10,"element":547},{"value":9,"element":668},{"value":9,"element":694},{"value":8,"element":683},{"value":7,"element":531},{"value":7,"element":532},{"value":7,"element":552},{"value":7,"element":724},{"value":6,"element":560},{"value":4,"element":553},{"value":3,"element":735},{"value":2,"element":548},{"value":1,"element":543}],"h":[{"value":8,"element":408},{"value":8,"element":411},{"value":8,"element":423},{"value":6,"element":407},{"value":6,"element":417},{"value":5,"element":416},{"value":4,"element":403},{"value":4,"element":418},{"value":3,"element":414},{"value":3,"element":430},{"value":1,"element":405},{"value":1,"element":413},{"value":1,"element":415}]}],"team_h_difficulty":2,"team_a_difficulty":4,"pulse_id":124937},{"code":2562042,"event":15,"finished":true,"finished_provisional":true,"id":148,"kickoff_time":"2025-12-06T15:00:00Z","minutes":90,"provisional_start_time":false,"started":true,"team_a":3,"team_a_score":1,"team_h":15,"team_h_score":2,"stats":[{"identifier":"goals_scored","a":[{"value":1,"element":215}],"h":[{"value":1,"element":485},{"value":1,"element":488}]},{"identifier":"assists","a":[],"h":[]},{"identifier":"own_goals","a":[],"h":[]},{"identifier":"penalties_saved","a":[],"h":[]},{"identifier":"penalties_missed","a":[],"h":[]},{"identifier":"yellow_cards","a":[{"value":1,"element":187},{"value":1,"element":209}],"h":[{"value":1,"element":52},{"value":1,"element":477}]},{"identifier":"red_cards","a":[{"value":1,"element":195}],"h":[]},{"identifier":"saves","a":[{"value":6,"element":470}],"h":[{"value":2,"element":674}]},{"identifier":"bonus","a":[],"h":[{"value":3,"element":488},{"value":2,"element":485},{"value":1,"element":476}]},{"identifier":"bps","a":[{"value":17,"element":205},{"value":14,"element":215},{"value":13,"element":470},{"value":10,"element":202},{"value":8,"element":206},{"value":6,"element":191},{"value":6,"element":722},{"value":5,"element":199},{"value":5,"element":676},{"value":3,"element":200},{"value":3,"element":209},{"value":2,"element":217},{"value":-1,"element":680},{"value":-5,"element":187},{"value":-11,"element":195}],"h":[{"value":44,"element":488},{"value":32,"element":485},{"value":28,"element":476},{"value":17,"element":477},{"value":14,"element":494},{"value":14,"element":684},{"value":13,"element":674},{"value":12,"element":473},{"value":9,"element":474},{"value":8,"element":52},{"value":7,"element":486},{"value":6,"element":490},{"value":6,"element":714},{"value":4,"element":497},{"value":3,"element":491},{"value":2,"element":135}]},{"identifier":"defensive_contribution","a":[{"value":10,"element":191},{"value":10,"element":202},{"value":9,"element":676},{"value":8,"element":190},{"value":8,"element":199},{"value":7,"element":722},{"value":5,"element":209},{"value":5,"element":680},{"value":4,"element":205},{"value":1,"element":187},{"value":1,"element":195},{"value":1,"element":200},{"value":1,"element":215}],"h":[{"value":11,"element":52},{"value":8,"element":684},{"value":7,"element":477},{"value":7,"element":488},{"value":6,"element":473},{"value":6,"element":474},{"value":5,"element":476},{"value":5,"element":485},{"value":3,"element":490},{"value":3,"element":494},{"value":3,"element":714},{"value":1,"element":135},{"value":1,"element":486},{"value":1,"element":491},{"value":1,"element":497}]}],"team_h_difficulty":2,"team_a_difficulty":4,"pulse_id":124938},{"code":2562043,"event":15,"finished":true,"finished_provisional":true,"id":149,"kickoff_time":"2025-12-06T15:00:00Z","minutes":90,"provisional_start_time":false,"started":true,"team_a":5,"team_a_score":0,"team_h":18,"team_h_score":2,"stats":[{"identifier":"goals_scored","a":[],"h":[{"value":1,"element":597},{"value":1,"element":717}]},{"identifier":"assists","a":[],"h":[{"value":1,"element":717}]},{"identifier":"own_goals","a":[],"h":[]},{"identifier":"penalties_saved","a":[],"h":[]},{"identifier":"penalties_missed","a":[],"h":[]},{"identifier":"yellow_cards","a":[{"value":1,"element":108},{"value":1,"element":110},{"value":1,"element":120},{"value":1,"element":129}],"h":[{"value":1,"element":568},{"value":1,"element":569},{"value":1,"element":591}]},{"identifier":"red_cards","a":[],"h":[]},{"identifier":"saves","a":[{"value":5,"element":101}],"h":[{"value":1,"element":565}]},{"identifier":"bonus","a":[],"h":[{"value":3,"element":717},{"value":2,"element":597},{"value":1,"element":569}]},{"identifier":"bps","a":[{"value":16,"element":106},{"value":15,"element":83},{"value":14,"element":101},{"value":14,"element":124},{"value":11,"element":110},{"value":6,"element":120},{"value":5,"element":125},{"value":4,"element":109},{"value":4,"element":126},{"value":4,"element":136},{"value":3,"element":107},{"value":3,"element":113},{"value":3,"element":116},{"value":3,"element":129},{"value":2,"element":121},{"value":-7,"element":108}],"h":[{"value":47,"element":717},{"value":37,"element":597},{"value":29,"element":569},{"value":26,"element":568},{"value":25,"element":573},{"value":25,"element":575},{"value":25,"element":582},{"value":24,"element":565},{"value":16,"element":585},{"value":10,"element":591},{"value":6,"element":673},{"value":3,"element":588},{"value":2,"element":570},{"value":2,"element":593},{"value":-1,"element":726}]},{"identifier":"defensive_contribution","a":[{"value":14,"element":124},{"value":13,"element":83},{"value":11,"element":106},{"value":9,"element":110},{"value":7,"element":120},{"value":6,"element":129},{"value":5,"element":113},{"value":5,"element":136},{"value":4,"element":109},{"value":4,"element":121},{"value":3,"element":108},{"value":1,"element":126}],"h":[{"value":15,"element":585},{"value":9,"element":582},{"value":9,"element":591},{"value":9,"element":597},{"value":9,"element":717},{"value":8,"element":568},{"value":8,"element":569},{"value":7,"element":575},{"value":5,"element":673},{"value":5,"element":726},{"value":4,"element":573},{"value":2,"element":570},{"value":1,"element":588},{"value":1,"element":593}]}],"team_h_difficulty":3,"team_a_difficulty":3,"pulse_id":124939},{"code":2562040,"event":15,"finished":true,"finished_provisional":true,"id":146,"kickoff_time":"2025-12-06T17:30:00Z","minutes":90,"provisional_start_time":false,"started":true,"team_a":12,"team_a_score":3,"team_h":11,"team_h_score":3,"stats":[{"identifier":"goals_scored","a":[{"value":2,"element":661},{"value":1,"element":387}],"h":[{"value":1,"element":358},{"value":1,"element":660},{"value":1,"element":691}]},{"identifier":"assists","a":[{"value":1,"element":390}],"h":[{"value":1,"element":350},{"value":1,"element":351},{"value":1,"element":660}]},{"identifier":"own_goals","a":[],"h":[]},{"identifier":"penalties_saved","a":[],"h":[]},{"identifier":"penalties_missed","a":[],"h":[]},{"identifier":"yellow_cards","a":[{"value":1,"element":373},{"value":1,"element":375},{"value":1,"element":376}],"h":[{"value":1,"element":342},{"value":1,"element":343},{"value":1,"element":347}]},{"identifier":"red_cards","a":[],"h":[]},{"identifier":"saves","a":[{"value":2,"element":366}],"h":[{"value":4,"element":665}]},{"identifier":"bonus","a":[{"value":3,"element":661},{"value":1,"element":387}],"h":[{"value":2,"element":660}]},{"identifier":"bps","a":[{"value":56,"element":661},{"value":37,"element":387},{"value":29,"element":390},{"value":25,"element":375},{"value":19,"element":388},{"value":11,"element":382},{"value":11,"element":384},{"value":6,"element":386},{"value":4,"element":374},{"value":3,"element":392},{"value":2,"element":366},{"value":2,"element":371},{"value":2,"element":373},{"value":2,"element":499},{"value":-12,"element":376}],"h":[{"value":46,"element":660},{"value":25,"element":358},{"value":15,"element":354},{"value":14,"element":350},{"value":13,"element":351},{"value":10,"element":356},{"value":9,"element":665},{"value":9,"element":691},{"value":7,"element":344},{"value":3,"element":345},{"value":3,"element":698},{"value":2,"element":348},{"value":2,"element":362},{"value":-2,"element":347},{"value":-9,"element":342}]},{"identifier":"defensive_contribution","a":[{"value":16,"element":373},{"value":10,"element":390},{"value":9,"element":388},{"value":8,"element":374},{"value":8,"element":387},{"value":6,"element":371},{"value":4,"element":375},{"value":4,"element":386},{"value":4,"element":661},{"value":3,"element":376},{"value":3,"element":384},{"value":1,"element":382},{"value":1,"element":392}],"h":[{"value":9,"element":348},{"value":9,"element":660},{"value":8,"element":354},{"value":7,"element":344},{"value":5,"element":343},{"value":4,"element":342},{"value":4,"element":356},{"value":3,"element":347},{"value":3,"element":358},{"value":3,"element":691},{"value":2,"element":698}]}],"team_h_difficulty":4,"team_a_difficulty":3,"pulse_id":124936},{"code":2562037,"event":15,"finished":true,"finished_provisional":true,"id":143,"kickoff_time":"2025-12-07T14:00:00Z","minutes":90,"provisional_start_time":false,"started":true,"team_a":19,"team_a_score":1,"team_h":6,"team_h_score":1,"stats":[{"identifier":"goals_scored","a":[{"value":1,"element":624}],"h":[{"value":1,"element":158}]},{"identifier":"assists","a":[{"value":1,"element":671}],"h":[{"value":1,"element":151}]},{"identifier":"own_goals","a":[],"h":[]},{"identifier":"penalties_saved","a":[],"h":[]},{"identifier":"penalties_missed","a":[],"h":[]},{"identifier":"yellow_cards","a":[{"value":1,"element":618},{"value":1,"element":623}],"h":[{"value":1,"element":146},{"value":1,"element":148}]},{"identifier":"red_cards","a":[],"h":[]},{"identifier":"saves","a":[{"value":4,"element":600}],"h":[{"value":4,"element":139}]},{"identifier":"bonus","a":[{"value":3,"element":624}],"h":[{"value":2,"element":145},{"value":1,"element":158}]},{"identifier":"bps","a":[{"value":36,"element":624},{"value":30,"element":708},{"value":19,"element":603},{"value":19,"element":612},{"value":14,"element":610},{"value":13,"element":600},{"value":11,"element":671},{"value":9,"element":606},{"value":7,"element":609},{"value":6,"element":605},{"value":5,"element":618},{"value":3,"element":623},{"value":3,"element":718},{"value":2,"element":613}],"h":[{"value":35,"element":145},{"value":33,"element":158},{"value":23,"element":151},{"value":22,"element":139},{"value":14,"element":146},{"value":13,"element":169},{"value":9,"element":173},{"value":6,"element":148},{"value":6,"element":162},{"value":4,"element":143},{"value":4,"element":160},{"value":4,"element":163},{"value":4,"element":178},{"value":3,"element":167},{"value":2,"element":181}]},{"identifier":"defensive_contribution","a":[{"value":23,"element":708},{"value":14,"element":606},{"value":11,"element":605},{"value":10,"element":610},{"value":9,"element":609},{"value":7,"element":624},{"value":6,"element":603},{"value":5,"element":618},{"value":4,"element":615},{"value":3,"element":612},{"value":2,"element":671},{"value":2,"element":747},{"value":1,"element":613},{"value":1,"element":623}],"h":[{"value":11,"element":169},{"value":9,"element":146},{"value":7,"element":158},{"value":6,"element":151},{"value":4,"element":167},{"value":4,"element":173},{"value":3,"element":145},{"value":3,"element":178},{"value":3,"element":181},{"value":2,"element":148},{"value":2,"element":160},{"value":1,"element":162},{"value":1,"element":163}]}],"team_h_difficulty":2,"team_a_difficulty":3,"pulse_id":124933},{"code":2562039,"event":15,"finished":true,"finished_provisional":true,"id":145,"kickoff_time":"2025-12-07T16:30:00Z","minutes":90,"provisional_start_time":false,"started":true,"team_a":8,"team_a_score":2,"team_h":10,"team_h_score":1,"stats":[{"identifier":"goals_scored","a":[{"value":1,"element":260},{"value":1,"element":284}],"h":[{"value":1,"element":329}]},{"identifier":"assists","a":[{"value":1,"element":273},{"value":1,"element":712}],"h":[{"value":1,"element":337}]},{"identifier":"own_goals","a":[],"h":[]},{"identifier":"penalties_saved","a":[],"h":[]},{"identifier":"penalties_missed","a":[],"h":[]},{"identifier":"yellow_cards","a":[],"h":[]},{"identifier":"red_cards","a":[],"h":[]},{"identifier":"saves","a":[{"value":3,"element":253}],"h":[{"value":3,"element":314}]},{"identifier":"bonus","a":[{"value":3,"element":284},{"value":2,"element":273}],"h":[{"value":1,"element":329}]},{"identifier":"bps","a":[{"value":34,"element":284},{"value":33,"element":273},{"value":29,"element":712},{"value":28,"element":260},{"value":16,"element":271},{"value":14,"element":253},{"value":13,"element":258},{"value":11,"element":261},{"value":10,"element":263},{"value":9,"element":257},{"value":5,"element":272},{"value":4,"element":283},{"value":3,"element":723},{"value":2,"element":276},{"value":1,"element":732}],"h":[{"value":30,"element":329},{"value":19,"element":324},{"value":14,"element":317},{"value":14,"element":330},{"value":13,"element":322},{"value":11,"element":337},{"value":10,"element":727},{"value":8,"element":314},{"value":8,"element":318},{"value":8,"element":325},{"value":6,"element":319},{"value":5,"element":332},{"value":4,"element":331},{"value":3,"element":326},{"value":2,"element":335}]},{"identifier":"defensive_contribution","a":[{"value":14,"element":273},{"value":11,"element":261},{"value":9,"element":263},{"value":8,"element":258},{"value":7,"element":271},{"value":6,"element":257},{"value":6,"element":283},{"value":5,"element":260},{"value":5,"element":284},{"value":5,"element":712},{"value":3,"element":272},{"value":2,"element":732},{"value":1,"element":276}],"h":[{"value":12,"element":322},{"value":10,"element":318},{"value":8,"element":727},{"value":7,"element":317},{"value":6,"element":324},{"value":5,"element":325},{"value":5,"element":329},{"value":5,"element":330},{"value":5,"element":337},{"value":4,"element":332},{"value":3,"element":319},{"value":2,"element":731},{"value":1,"element":335}]}],"team_h_difficulty":3,"team_a_difficulty":3,"pulse_id":124935},{"code":2562044,"event":15,"finished":true,"finished_provisional":true,"id":150,"kickoff_time":"2025-12-08T20:00:00Z","minutes":90,"provisional_start_time":false,"started":true,"team_a":14,"team_a_score":4,"team_h":20,"team_h_score":1,"stats":[{"identifier":"goals_scored","a":[{"value":2,"element":449},{"value":1,"element":119},{"value":1,"element":455}],"h":[{"value":1,"element":644}]},{"identifier":"assists","a":[{"value":1,"element":440},{"value":1,"element":449},{"value":1,"element":450},{"value":1,"element":452}],"h":[{"value":1,"element":682}]},{"identifier":"own_goals","a":[],"h":[]},{"identifier":"penalties_saved","a":[],"h":[]},{"identifier":"penalties_missed","a":[],"h":[]},{"identifier":"yellow_cards","a":[{"value":1,"element":119},{"value":1,"element":466}],"h":[{"value":1,"element":634},{"value":1,"element":654},{"value":1,"element":709}]},{"identifier":"red_cards","a":[],"h":[]},{"identifier":"saves","a":[{"value":1,"element":733}],"h":[{"value":4,"element":627}]},{"identifier":"bonus","a":[{"value":3,"element":449},{"value":2,"element":119},{"value":1,"element":452}],"h":[]},{"identifier":"bps","a":[{"value":74,"element":449},{"value":32,"element":119},{"value":27,"element":452},{"value":26,"element":450},{"value":22,"element":455},{"value":20,"element":440},{"value":14,"element":447},{"value":11,"element":438},{"value":11,"element":443},{"value":10,"element":457},{"value":8,"element":733},{"value":6,"element":444},{"value":5,"element":437},{"value":4,"element":458},{"value":3,"element":441}],"h":[{"value":23,"element":644},{"value":12,"element":631},{"value":9,"element":643},{"value":9,"element":663},{"value":7,"element":637},{"value":7,"element":749},{"value":6,"element":627},{"value":5,"element":695},{"value":3,"element":638},{"value":2,"element":645},{"value":2,"element":720},{"value":1,"element":682},{"value":-1,"element":634},{"value":-3,"element":633},{"value":-8,"element":709}]},{"identifier":"defensive_contribution","a":[{"value":10,"element":119},{"value":9,"element":457},{"value":8,"element":447},{"value":8,"element":449},{"value":7,"element":438},{"value":7,"element":440},{"value":7,"element":450},{"value":6,"element":443},{"value":6,"element":452},{"value":4,"element":455},{"value":3,"element":444},{"value":1,"element":437},{"value":1,"element":466}],"h":[{"value":15,"element":631},{"value":11,"element":643},{"value":11,"element":709},{"value":9,"element":634},{"value":9,"element":644},{"value":9,"element":663},{"value":8,"element":638},{"value":7,"element":637},{"value":6,"element":749},{"value":4,"element":682},{"value":3,"element":645},{"value":2,"element":633},{"value":2,"element":654}]}],"team_h_difficulty":3,"team_a_difficulty":2,"pulse_id":124940}]