{"fixtures":[],"history":[{"element":37,"fixture":7,"opponent_team":18,"total_points":6,"was_home":false,"kickoff_time":"2019-08-10T14:00:00Z","team_h_score":0,"team_a_score":3,"round":1,"minutes":90,"goals_scored":0,"assists":0,"clean_sheets":1,"goals_conceded":0,"own_goals":0,"penalties_saved":0,"penalties_missed":0,"yellow_cards":0,"red_cards":0,"saves":0,"bonus":0,"bps":26,"influence":"22.6","creativity":"0.2","threat":"2.0","ict_index":"2.5","value":50,"transfers_balance":0,"selected":165358,"transfers_in":0,"transfers_out":0},{"element":37,"fixture":13,"opponent_team":19,"total_points":2,"was_home":true,"kickoff_time":"2019-08-17T14:00:00Z","team_h_score":1,"team_a_score":1,"round":2,"minutes":90,"goals_scored":0,"assists":0,"clean_sheets":0,"goals_conceded":1,"own_goals":0,"penalties_saved":0,"penalties_missed":0,"yellow_cards":0,"red_cards":0,"saves":0,"bonus":0,"bps":13,"influence":"9.4","creativity":"0.8","threat":"3.0","ict_index":"1.3","value":50,"transfers_balance":-114,"selected":178478,"transfers_in":10310,"transfers_out":10424},{"element":37,"fixture":23,"opponent_team":16,"total_points":1,"was_home":true,"kickoff_time":"2019-08-24T14:00:00Z","team_h_score":0,"team_a_score":2,"round":3,"minutes":90,"goals_scored":0,"assists":0,"clean_sheets":0,"goals_conceded":2,"own_goals":0,"penalties_saved":0,"penalties_missed":0,"yellow_cards":0,"red_cards":0,"saves":0,"bonus":0,"bps":13,"influence":"10.8","creativity":"0.2","threat":"6.0","ict_index":"1.7","value":50,"transfers_balance":-5096,"selected":177105,"transfers_in":10632,"transfers_out":15728},{"element":37,"fixture":37,"opponent_team":11,"total_points":0,"was_home":false,"kickoff_time":"2019-08-31T14:00:00Z","team_h_score":4,"team_a_score":0,"round":4,"minutes":0,"goals_scored":0,"assists":0,"clean_sheets":0,"goals_conceded":0,"own_goals":0,"penalties_saved":0,"penalties_missed":0,"yellow_cards":0,"red_cards":0,"saves":0,"bonus":0,"bps":0,"influence":"0.0","creativity":"0.0","threat":"0.0","ict_index":"0.0","value":50,"transfers_balance":-16696,"selected":160955,"transfers_in":3506,"transfers_out":20202},{"element":37,"fixture":43,"opponent_team":5,"total_points":2,"was_home":true,"kickoff_time":"2019-09-14T14:00:00Z","team_h_score":1,"team_a_score":1,"round":5,"minutes":90,"goals_scored":0,"assists":0,"clean_sheets":0,"goals_conceded":1,"own_goals":0,"penalties_saved":0,"penalties_missed":0,"yellow_cards":0,"red_cards":0,"saves":0,"bonus":0,"bps":13,"influence":"21.4","creativity":"0.4","threat":"2.0","ict_index":"2.4","value":50,"transfers_balance":-11376,"selected":151728,"transfers_in":5069,"transfers_out":16445},{"element":37,"fixture":58,"opponent_team":13,"total_points":0,"was_home":false,"kickoff_time":"2019-09-21T16:30:00Z","team_h_score":0,"team_a_score":0,"round":6,"minutes":0,"goals_scored":0,"assists":0,"clean_sheets":0,"goals_conceded":0,"own_goals":0,"penalties_saved":0,"penalties_missed":0,"yellow_cards":0,"red_cards":0,"saves":0,"bonus":0,"bps":0,"influence":"0.0","creativity":"0.0","threat":"0.0","ict_index":"0.0","value":50,"transfers_balance":-6997,"selected":145543,"transfers_in":1844,"transfers_out":8841},{"element":37,"fixture":63,"opponent_team":6,"total_points":0,"was_home":false,"kickoff_time":"2019-09-28T14:00:00Z","team_h_score":2,"team_a_score":0,"round":7,"minutes":0,"goals_scored":0,"assists":0,"clean_sheets":0,"goals_conceded":0,"own_goals":0,"penalties_saved":0,"penalties_missed":0,"yellow_cards":0,"red_cards":0,"saves":0,"bonus":0,"bps":0,"influence":"0.0","creativity":"0.0","threat":"0.0","ict_index":"0.0","value":49,"transfers_balance":-29366,"selected":115984,"transfers_in":655,"transfers_out":30021},{"element":37,"fixture":72,"opponent_team":17,"total_points":0,"was_home":true,"kickoff_time":"2019-10-05T11:30:00Z","team_h_score":3,"team_a_score":0,"round":8,"minutes":0,"goals_scored":0,"assists":0,"clean_sheets":0,"goals_conceded":0,"own_goals":0,"penalties_saved":0,"penalties_missed":0,"yellow_cards":0,"red_cards":0,"saves":0,"bonus":0,"bps":0,"influence":"0.0","creativity":"0.0","threat":"0.0","ict_index":"0.0","value":49,"transfers_balance":-24246,"selected":91824,"transfers_in":23,"transfers_out":24269},{"element":37,"fixture":81,"opponent_team":2,"total_points":1,"was_home":false,"kickoff_time":"2019-10-19T14:00:00Z","team_h_score":2,"team_a_score":1,"round":9,"minutes":20,"goals_scored":0,"assists":0,"clean_sheets":0,"goals_conceded":1,"own_goals":0,"penalties_saved":0,"penalties_missed":0,"yellow_cards":0,"red_cards":0,"saves":0,"bonus":0,"bps":5,"influence":"11.2","creativity":"0.0","threat":"0.0","ict_index":"1.1","value":49,"transfers_balance":-7559,"selected":85154,"transfers_in":710,"transfers_out":8269},{"element":37,"fixture":92,"opponent_team":8,"total_points":0,"was_home":true,"kickoff_time":"2019-10-26T14:00:00Z","team_h_score":3,"team_a_score":2,"round":10,"minutes":0,"goals_scored":0,"assists":0,"clean_sheets":0,"goals_conceded":0,"own_goals":0,"penalties_saved":0,"penalties_missed":0,"yellow_cards":0,"red_cards":0,"saves":0,"bonus":0,"bps":0,"influence":"0.0","creativity":"0.0","threat":"0.0","ict_index":"0.0","value":49,"transfers_balance":-1564,"selected":84065,"transfers_in":851,"transfers_out":2415},{"element":37,"fixture":104,"opponent_team":14,"total_points":7,"was_home":true,"kickoff_time":"2019-11-02T15:00:00Z","team_h_score":2,"team_a_score":0,"round":11,"minutes":54,"goals_scored":1,"assists":0,"clean_sheets":0,"goals_conceded":0,"own_goals":0,"penalties_saved":0,"penalties_missed":0,"yellow_cards":0,"red_cards":0,"saves":0,"bonus":0,"bps":20,"influence":"38.2","creativity":"0.8","threat":"21.0","ict_index":"6.0","value":49,"transfers_balance":-2841,"selected":81486,"transfers_in":1296,"transfers_out":4137},{"element":37,"fixture":115,"opponent_team":12,"total_points":1,"was_home":false,"kickoff_time":"2019-11-10T14:00:00Z","team_h_score":3,"team_a_score":1,"round":12,"minutes":90,"goals_scored":0,"assists":0,"clean_sheets":0,"goals_conceded":3,"own_goals":0,"penalties_saved":0,"penalties_missed":0,"yellow_cards":0,"red_cards":0,"saves":0,"bonus":0,"bps":14,"influence":"30.8","creativity":"0.5","threat":"7.0","ict_index":"3.8","value":49,"transfers_balance":-432,"selected":81352,"transfers_in":1702,"transfers_out":2134},{"element":37,"fixture":124,"opponent_team":9,"total_points":1,"was_home":true,"kickoff_time":"2019-11-23T15:00:00Z","team_h_score":0,"team_a_score":2,"round":13,"minutes":90,"goals_scored":0,"assists":0,"clean_sheets":0,"goals_conceded":2,"own_goals":0,"penalties_saved":0,"penalties_missed":0,"yellow_cards":0,"red_cards":0,"saves":0,"bonus":0,"bps":4,"influence":"0.0","creativity":"0.6","threat":"11.0","ict_index":"1.1","value":49,"transfers_balance":-1187,"selected":80566,"transfers_in":1771,"transfers_out":2958},{"element":37,"fixture":134,"opponent_team":10,"total_points":0,"was_home":false,"kickoff_time":"2019-11-30T15:00:00Z","team_h_score":2,"team_a_score":1,"round":14,"minutes":0,"goals_scored":0,"assists":0,"clean_sheets":0,"goals_conceded":0,"own_goals":0,"penalties_saved":0,"penalties_missed":0,"yellow_cards":0,"red_cards":0,"saves":0,"bonus":0,"bps":0,"influence":"0.0","creativity":"0.0","threat":"0.0","ict_index":"0.0","value":49,"transfers_balance":-1847,"selected":78840,"transfers_in":562,"transfers_out":2409},{"element":37,"fixture":141,"opponent_team":1,"total_points":1,"was_home":false,"kickoff_time":"2019-12-05T20:15:00Z","team_h_score":1,"team_a_score":2,"round":15,"minutes":2,"goals_scored":0,"assists":0,"clean_sheets":0,"goals_conceded":0,"own_goals":0,"penalties_saved":0,"penalties_missed":0,"yellow_cards":0,"red_cards":0,"saves":0,"bonus":0,"bps":3,"influence":"0.2","creativity":"0.0","threat":"0.0","ict_index":"0.0","value":49,"transfers_balance":-1507,"selected":77497,"transfers_in":430,"transfers_out":1937},{"element":37,"fixture":153,"opponent_team":20,"total_points":0,"was_home":true,"kickoff_time":"2019-12-08T16:30:00Z","team_h_score":2,"team_a_score":2,"round":16,"minutes":0,"goals_scored":0,"assists":0,"clean_sheets":0,"goals_conceded":0,"own_goals":0,"penalties_saved":0,"penalties_missed":0,"yellow_cards":0,"red_cards":0,"saves":0,"bonus":0,"bps":0,"influence":"0.0","creativity":"0.0","threat":"0.0","ict_index":"0.0","value":49,"transfers_balance":-1335,"selected":76330,"transfers_in":756,"transfers_out":2091},{"element":37,"fixture":164,"opponent_team":7,"total_points":1,"was_home":false,"kickoff_time":"2019-12-16T19:45:00Z","team_h_score":1,"team_a_score":1,"round":17,"minutes":5,"goals_scored":0,"assists":0,"clean_sheets":0,"goals_conceded":0,"own_goals":0,"penalties_saved":0,"penalties_missed":0,"yellow_cards":0,"red_cards":0,"saves":0,"bonus":0,"bps":3,"influence":"0.2","creativity":"0.0","threat":"0.0","ict_index":"0.0","value":48,"transfers_balance":-1691,"selected":74842,"transfers_in":967,"transfers_out":2658},{"element":37,"fixture":173,"opponent_team":15,"total_points":0,"was_home":true,"kickoff_time":"2019-12-21T15:00:00Z","team_h_score":0,"team_a_score":1,"round":18,"minutes":0,"goals_scored":0,"assists":0,"clean_sheets":0,"goals_conceded":0,"own_goals":0,"penalties_saved":0,"penalties_missed":0,"yellow_cards":0,"red_cards":0,"saves":0,"bonus":0,"bps":0,"influence":"0.0","creativity":"0.0","threat":"0.0","ict_index":"0.0","value":48,"transfers_balance":-675,"selected":74665,"transfers_in":1353,"transfers_out":2028},{"element":37,"fixture":189,"opponent_team":17,"total_points":1,"was_home":false,"kickoff_time":"2019-12-26T12:30:00Z","team_h_score":2,"team_a_score":1,"round":19,"minutes":90,"goals_scored":0,"assists":0,"clean_sheets":0,"goals_conceded":2,"own_goals":0,"penalties_saved":0,"penalties_missed":0,"yellow_cards":0,"red_cards":0,"saves":0,"bonus":0,"bps":12,"influence":"22.8","creativity":"0.0","threat":"2.0","ict_index":"2.5","value":48,"transfers_balance":-1681,"selected":72893,"transfers_in":413,"transfers_out":2094},{"element":37,"fixture":192,"opponent_team":3,"total_points":6,"was_home":true,"kickoff_time":"2019-12-28T12:30:00Z","team_h_score":2,"team_a_score":0,"round":20,"minutes":90,"goals_scored":0,"assists":0,"clean_sheets":1,"goals_conceded":0,"own_goals":0,"penalties_saved":0,"penalties_missed":0,"yellow_cards":0,"red_cards":0,"saves":0,"bonus":0,"bps":21,"influence":"7.2","creativity":"0.6","threat":"2.0","ict_index":"1.0","value":48,"transfers_balance":363,"selected":73616,"transfers_in":1569,"transfers_out":1206},{"element":37,"fixture":202,"opponent_team":6,"total_points":0,"was_home":true,"kickoff_time":"2020-01-01T12:30:00Z","team_h_score":1,"team_a_score":1,"round":21,"minutes":0,"goals_scored":0,"assists":0,"clean_sheets":0,"goals_conceded":0,"own_goals":0,"penalties_saved":0,"penalties_missed":0,"yellow_cards":0,"red_cards":0,"saves":0,"bonus":0,"bps":0,"influence":"0.0","creativity":"0.0","threat":"0.0","ict_index":"0.0","value":48,"transfers_balance":665,"selected":74389,"transfers_in":2429,"transfers_out":1764},{"element":37,"fixture":215,"opponent_team":8,"total_points":1,"was_home":false,"kickoff_time":"2020-01-11T15:00:00Z","team_h_score":1,"team_a_score":0,"round":22,"minutes":90,"goals_scored":0,"assists":0,"clean_sheets":0,"goals_conceded":1,"own_goals":0,"penalties_saved":0,"penalties_missed":0,"yellow_cards":1,"red_cards":0,"saves":0,"bonus":0,"bps":11,"influence":"28.4","creativity":"10.3","threat":"0.0","ict_index":"3.9","value":48,"transfers_balance":-1406,"selected":73172,"transfers_in":1035,"transfers_out":2441},{"element":37,"fixture":222,"opponent_team":2,"total_points":0,"was_home":true,"kickoff_time":"2020-01-18T15:00:00Z","team_h_score":1,"team_a_score":1,"round":23,"minutes":0,"goals_scored":0,"assists":0,"clean_sheets":0,"goals_conceded":0,"own_goals":0,"penalties_saved":0,"penalties_missed":0,"yellow_cards":0,"red_cards":0,"saves":0,"bonus":0,"bps":0,"influence":"0.0","creativity":"0.0","threat":"0.0","ict_index":"0.0","value":48,"transfers_balance":-657,"selected":72712,"transfers_in":1116,"transfers_out":1773},{"element":37,"fixture":232,"opponent_team":3,"total_points":0,"was_home":false,"kickoff_time":"2020-01-21T19:30:00Z","team_h_score":3,"team_a_score":1,"round":24,"minutes":0,"goals_scored":0,"assists":0,"clean_sheets":0,"goals_conceded":0,"own_goals":0,"penalties_saved":0,"penalties_missed":0,"yellow_cards":0,"red_cards":0,"saves":0,"bonus":0,"bps":0,"influence":"0.0","creativity":"0.0","threat":"0.0","ict_index":"0.0","value":48,"transfers_balance":-1528,"selected":71125,"transfers_in":439,"transfers_out":1967},{"element":37,"fixture":250,"opponent_team":19,"total_points":0,"was_home":false,"kickoff_time":"2020-02-01T15:00:00Z","team_h_score":3,"team_a_score":3,"round":25,"minutes":0,"goals_scored":0,"assists":0,"clean_sheets":0,"goals_conceded":0,"own_goals":0,"penalties_saved":0,"penalties_missed":0,"yellow_cards":0,"red_cards":0,"saves":0,"bonus":0,"bps":0,"influence":"0.0","creativity":"0.0","threat":"0.0","ict_index":"0.0","value":48,"transfers_balance":-2995,"selected":68293,"transfers_in":253,"transfers_out":3248},{"element":37,"fixture":253,"opponent_team":18,"total_points":2,"was_home":true,"kickoff_time":"2020-02-08T17:30:00Z","team_h_score":1,"team_a_score":1,"round":26,"minutes":90,"goals_scored":0,"assists":0,"clean_sheets":0,"goals_conceded":1,"own_goals":0,"penalties_saved":0,"penalties_missed":0,"yellow_cards":0,"red_cards":0,"saves":0,"bonus":0,"bps":9,"influence":"16.2","creativity":"5.0","threat":"4.0","ict_index":"2.5","value":48,"transfers_balance":-2189,"selected":66174,"transfers_in":44,"transfers_out":2233},{"element":37,"fixture":268,"opponent_team":15,"total_points":3,"was_home":false,"kickoff_time":"2020-02-22T15:00:00Z","team_h_score":1,"team_a_score":1,"round":27,"minutes":90,"goals_scored":0,"assists":0,"clean_sheets":0,"goals_conceded":1,"own_goals":0,"penalties_saved":0,"penalties_missed":0,"yellow_cards":0,"red_cards":0,"saves":0,"bonus":1,"bps":20,"influence":"34.6","creativity":"10.0","threat":"36.0","ict_index":"8.1","value":48,"transfers_balance":-463,"selected":65868,"transfers_in":270,"transfers_out":733},{"element":37,"fixture":273,"opponent_team":7,"total_points":0,"was_home":true,"kickoff_time":"2020-02-29T12:30:00Z","team_h_score":0,"team_a_score":1,"round":28,"minutes":0,"goals_scored":0,"assists":0,"clean_sheets":0,"goals_conceded":0,"own_goals":0,"penalties_saved":0,"penalties_missed":0,"yellow_cards":0,"red_cards":0,"saves":0,"bonus":0,"bps":0,"influence":"0.0","creativity":"0.0","threat":"0.0","ict_index":"0.0","value":48,"transfers_balance":171,"selected":66502,"transfers_in":742,"transfers_out":571},{"element":37,"fixture":290,"opponent_team":20,"total_points":0,"was_home":false,"kickoff_time":"2020-03-07T15:00:00Z","team_h_score":0,"team_a_score":0,"round":29,"minutes":0,"goals_scored":0,"assists":0,"clean_sheets":0,"goals_conceded":0,"own_goals":0,"penalties_saved":0,"penalties_missed":0,"yellow_cards":0,"red_cards":0,"saves":0,"bonus":0,"bps":0,"influence":"0.0","creativity":"0.0","threat":"0.0","ict_index":"0.0","value":48,"transfers_balance":-780,"selected":65349,"transfers_in":120,"transfers_out":900},{"element":37,"fixture":293,"opponent_team":1,"total_points":0,"was_home":true,"kickoff_time":"2020-06-20T14:00:00Z","team_h_score":2,"team_a_score":1,"round":39,"minutes":0,"goals_scored":0,"assists":0,"clean_sheets":0,"goals_conceded":0,"own_goals":0,"penalties_saved":0,"penalties_missed":0,"yellow_cards":0,"red_cards":0,"saves":0,"bonus":0,"bps":0,"influence":"0.0","creativity":"0.0","threat":"0.0","ict_index":"0.0","value":48,"transfers_balance":-887,"selected":64502,"transfers_in":1188,"transfers_out":2075},{"element":37,"fixture":303,"opponent_team":9,"total_points":5,"was_home":false,"kickoff_time":"2020-06-23T17:00:00Z","team_h_score":0,"team_a_score":0,"round":40,"minutes":66,"goals_scored":0,"assists":0,"clean_sheets":1,"goals_conceded":0,"own_goals":0,"penalties_saved":0,"penalties_missed":0,"yellow_cards":1,"red_cards":0,"saves":0,"bonus":0,"bps":19,"influence":"11.8","creativity":"0.0","threat":"0.0","ict_index":"1.2","value":48,"transfers_balance":-233,"selected":64444,"transfers_in":286,"transfers_out":519},{"element":37,"fixture":314,"opponent_team":12,"total_points":1,"was_home":true,"kickoff_time":"2020-06-30T19:15:00Z","team_h_score":0,"team_a_score":3,"round":41,"minutes":90,"goals_scored":0,"assists":0,"clean_sheets":0,"goals_conceded":3,"own_goals":0,"penalties_saved":0,"penalties_missed":0,"yellow_cards":0,"red_cards":0,"saves":0,"bonus":0,"bps":15,"influence":"14.4","creativity":"0.2","threat":"4.0","ict_index":"1.9","value":48,"transfers_balance":31,"selected":64577,"transfers_in":338,"transfers_out":307},{"element":37,"fixture":327,"opponent_team":14,"total_points":1,"was_home":false,"kickoff_time":"2020-07-04T11:30:00Z","team_h_score":0,"team_a_score":1,"round":42,"minutes":1,"goals_scored":0,"assists":0,"clean_sheets":0,"goals_conceded":0,"own_goals":0,"penalties_saved":0,"penalties_missed":0,"yellow_cards":0,"red_cards":0,"saves":0,"bonus":0,"bps":3,"influence":"0.0","creativity":"0.0","threat":"0.0","ict_index":"0.0","value":48,"transfers_balance":788,"selected":65632,"transfers_in":1286,"transfers_out":498},{"element":37,"fixture":334,"opponent_team":10,"total_points":0,"was_home":true,"kickoff_time":"2020-07-08T19:15:00Z","team_h_score":1,"team_a_score":3,"round":43,"minutes":0,"goals_scored":0,"assists":0,"clean_sheets":0,"goals_conceded":0,"own_goals":0,"penalties_saved":0,"penalties_missed":0,"yellow_cards":0,"red_cards":0,"saves":0,"bonus":0,"bps":0,"influence":"0.0","creativity":"0.0","threat":"0.0","ict_index":"0.0","value":48,"transfers_balance":-564,"selected":64916,"transfers_in":261,"transfers_out":825},{"element":37,"fixture":343,"opponent_team":11,"total_points":0,"was_home":true,"kickoff_time":"2020-07-11T19:00:00Z","team_h_score":0,"team_a_score":5,"round":44,"minutes":0,"goals_scored":0,"assists":0,"clean_sheets":0,"goals_conceded":0,"own_goals":0,"penalties_saved":0,"penalties_missed":0,"yellow_cards":0,"red_cards":0,"saves":0,"bonus":0,"bps":0,"influence":"0.0","creativity":"0.0","threat":"0.0","ict_index":"0.0","value":48,"transfers_balance":-467,"selected":64492,"transfers_in":152,"transfers_out":619},{"element":37,"fixture":359,"opponent_team":16,"total_points":0,"was_home":false,"kickoff_time":"2020-07-16T19:15:00Z","team_h_score":1,"team_a_score":1,"round":45,"minutes":0,"goals_scored":0,"assists":0,"clean_sheets":0,"goals_conceded":0,"own_goals":0,"penalties_saved":0,"penalties_missed":0,"yellow_cards":0,"red_cards":0,"saves":0,"bonus":0,"bps":0,"influence":"0.0","creativity":"0.0","threat":"0.0","ict_index":"0.0","value":48,"transfers_balance":-96,"selected":64464,"transfers_in":280,"transfers_out":376},{"element":37,"fixture":363,"opponent_team":13,"total_points":1,"was_home":true,"kickoff_time":"2020-07-20T17:00:00Z","team_h_score":0,"team_a_score":0,"round":46,"minutes":4,"goals_scored":0,"assists":0,"clean_sheets":0,"goals_conceded":0,"own_goals":0,"penalties_saved":0,"penalties_missed":0,"yellow_cards":0,"red_cards":0,"saves":0,"bonus":0,"bps":3,"influence":"7.8","creativity":"0.2","threat":"0.0","ict_index":"0.8","value":48,"transfers_balance":60,"selected":64649,"transfers_in":437,"transfers_out":377},{"element":37,"fixture":372,"opponent_team":5,"total_points":0,"was_home":false,"kickoff_time":"2020-07-26T15:00:00Z","team_h_score":1,"team_a_score":2,"round":47,"minutes":0,"goals_scored":0,"assists":0,"clean_sheets":0,"goals_conceded":0,"own_goals":0,"penalties_saved":0,"penalties_missed":0,"yellow_cards":0,"red_cards":0,"saves":0,"bonus":0,"bps":0,"influence":"0.0","creativity":"0.0","threat":"0.0","ict_index":"0.0","value":48,"transfers_balance":-174,"selected":64400,"transfers_in":372,"transfers_out":546}],"history_past":[{"season_name":"2009/10","element_code":61933,"start_cost":45,"end_cost":44,"total_points":0,"minutes":0,"goals_scored":0,"assists":0,"clean_sheets":0,"goals_conceded":0,"own_goals":0,"penalties_saved":0,"penalties_missed":0,"yellow_cards":0,"red_cards":0,"saves":0,"bonus":0,"bps":0,"influence":"0.0","creativity":"0.0","threat":"0.0","ict_index":"0.0"},{"season_name":"2010/11","element_code":61933,"start_cost":45,"end_cost":45,"total_points":0,"minutes":0,"goals_scored":0,"assists":0,"clean_sheets":0,"goals_conceded":0,"own_goals":0,"penalties_saved":0,"penalties_missed":0,"yellow_cards":0,"red_cards":0,"saves":0,"bonus":0,"bps":0,"influence":"0.0","creativity":"0.0","threat":"0.0","ict_index":"0.0"},{"season_name":"2011/12","element_code":61933,"start_cost":50,"end_cost":47,"total_points":6,"minutes":213,"goals_scored":0,"assists":0,"clean_sheets":0,"goals_conceded":3,"own_goals":0,"penalties_saved":0,"penalties_missed":0,"yellow_cards":0,"red_cards":0,"saves":0,"bonus":0,"bps":0,"influence":"0.0","creativity":"0.0","threat":"0.0","ict_index":"0.0"},{"season_name":"2012/13","element_code":61933,"start_cost":45,"end_cost":42,"total_points":1,"minutes":1,"goals_scored":0,"assists":0,"clean_sheets":0,"goals_conceded":0,"own_goals":0,"penalties_saved":0,"penalties_missed":0,"yellow_cards":0,"red_cards":0,"saves":0,"bonus":0,"bps":0,"influence":"0.0","creativity":"0.0","threat":"0.0","ict_index":"0.0"},{"season_name":"2013/14","element_code":61933,"start_cost":40,"end_cost":38,"total_points":0,"minutes":0,"goals_scored":0,"assists":0,"clean_sheets":0,"goals_conceded":0,"own_goals":0,"penalties_saved":0,"penalties_missed":0,"yellow_cards":0,"red_cards":0,"saves":0,"bonus":0,"bps":0,"influence":"0.0","creativity":"0.0","threat":"0.0","ict_index":"0.0"},{"season_name":"2014/15","element_code":61933,"start_cost":40,"end_cost":40,"total_points":0,"minutes":0,"goals_scored":0,"assists":0,"clean_sheets":0,"goals_conceded":0,"own_goals":0,"penalties_saved":0,"penalties_missed":0,"yellow_cards":0,"red_cards":0,"saves":0,"bonus":0,"bps":0,"influence":"0.0","creativity":"0.0","threat":"0.0","ict_index":"0.0"},{"season_name":"2017/18","element_code":61933,"start_cost":45,"end_cost":46,"total_points":100,"minutes":3292,"goals_scored":0,"assists":2,"clean_sheets":10,"goals_conceded":52,"own_goals":0,"penalties_saved":0,"penalties_missed":0,"yellow_cards":8,"red_cards":0,"saves":0,"bonus":7,"bps":614,"influence":"1027.6","creativity":"98.9","threat":"361.0","ict_index":"148.9"},{"season_name":"2018/19","element_code":61933,"start_cost":45,"end_cost":47,"total_points":115,"minutes":3087,"goals_scored":5,"assists":2,"clean_sheets":7,"goals_conceded":55,"own_goals":0,"penalties_saved":0,"penalties_missed":0,"yellow_cards":4,"red_cards":1,"saves":0,"bonus":9,"bps":582,"influence":"1024.4","creativity":"84.1","threat":"499.0","ict_index":"160.9"},{"season_name":"2019/20","element_code":61933,"start_cost":50,"end_cost":48,"total_points":44,"minutes":1232,"goals_scored":1,"assists":0,"clean_sheets":3,"goals_conceded":18,"own_goals":0,"penalties_saved":0,"penalties_missed":0,"yellow_cards":2,"red_cards":0,"saves":0,"bonus":1,"bps":227,"influence":"288.0","creativity":"29.8","threat":"100.0","ict_index":"41.8"}]}