{"fixtures":[],"history":[{"element":61,"fixture":2,"opponent_team":15,"total_points":10,"was_home":true,"kickoff_time":"2019-08-10T14:00:00Z","team_h_score":1,"team_a_score":1,"round":1,"minutes":90,"goals_scored":1,"assists":0,"clean_sheets":0,"goals_conceded":1,"own_goals":0,"penalties_saved":0,"penalties_missed":0,"yellow_cards":0,"red_cards":0,"saves":0,"bonus":2,"bps":24,"influence":"47.4","creativity":"1.2","threat":"68.0","ict_index":"11.7","value":45,"transfers_balance":0,"selected":8741,"transfers_in":0,"transfers_out":0},{"element":61,"fixture":12,"opponent_team":2,"total_points":0,"was_home":false,"kickoff_time":"2019-08-17T14:00:00Z","team_h_score":1,"team_a_score":2,"round":2,"minutes":0,"goals_scored":0,"assists":0,"clean_sheets":0,"goals_conceded":0,"own_goals":0,"penalties_saved":0,"penalties_missed":0,"yellow_cards":0,"red_cards":0,"saves":0,"bonus":0,"bps":0,"influence":"0.0","creativity":"0.0","threat":"0.0","ict_index":"0.0","value":45,"transfers_balance":41580,"selected":108632,"transfers_in":50181,"transfers_out":8601},{"element":61,"fixture":22,"opponent_team":11,"total_points":1,"was_home":true,"kickoff_time":"2019-08-25T13:00:00Z","team_h_score":1,"team_a_score":3,"round":3,"minutes":90,"goals_scored":0,"assists":0,"clean_sheets":0,"goals_conceded":3,"own_goals":0,"penalties_saved":0,"penalties_missed":0,"yellow_cards":0,"red_cards":0,"saves":0,"bonus":0,"bps":13,"influence":"19.2","creativity":"0.9","threat":"2.0","ict_index":"2.2","value":45,"transfers_balance":-7815,"selected":102003,"transfers_in":14971,"transfers_out":22786},{"element":61,"fixture":36,"opponent_team":9,"total_points":1,"was_home":false,"kickoff_time":"2019-08-31T14:00:00Z","team_h_score":3,"team_a_score":1,"round":4,"minutes":90,"goals_scored":0,"assists":0,"clean_sheets":0,"goals_conceded":3,"own_goals":0,"penalties_saved":0,"penalties_missed":0,"yellow_cards":0,"red_cards":0,"saves":0,"bonus":0,"bps":13,"influence":"25.0","creativity":"0.4","threat":"2.0","ict_index":"2.7","value":45,"transfers_balance":-593,"selected":103929,"transfers_in":10784,"transfers_out":11377},{"element":61,"fixture":42,"opponent_team":8,"total_points":1,"was_home":true,"kickoff_time":"2019-09-15T13:00:00Z","team_h_score":3,"team_a_score":1,"round":5,"minutes":1,"goals_scored":0,"assists":0,"clean_sheets":0,"goals_conceded":0,"own_goals":0,"penalties_saved":0,"penalties_missed":0,"yellow_cards":0,"red_cards":0,"saves":0,"bonus":0,"bps":3,"influence":"0.0","creativity":"0.0","threat":"0.0","ict_index":"0.0","value":45,"transfers_balance":-7810,"selected":96679,"transfers_in":5445,"transfers_out":13255},{"element":61,"fixture":59,"opponent_team":16,"total_points":0,"was_home":false,"kickoff_time":"2019-09-20T19:00:00Z","team_h_score":1,"team_a_score":3,"round":6,"minutes":0,"goals_scored":0,"assists":0,"clean_sheets":0,"goals_conceded":0,"own_goals":0,"penalties_saved":0,"penalties_missed":0,"yellow_cards":0,"red_cards":0,"saves":0,"bonus":0,"bps":0,"influence":"0.0","creativity":"0.0","threat":"0.0","ict_index":"0.0","value":45,"transfers_balance":-4402,"selected":93348,"transfers_in":1911,"transfers_out":6313},{"element":61,"fixture":62,"opponent_team":19,"total_points":0,"was_home":true,"kickoff_time":"2019-09-28T14:00:00Z","team_h_score":2,"team_a_score":2,"round":7,"minutes":0,"goals_scored":0,"assists":0,"clean_sheets":0,"goals_conceded":0,"own_goals":0,"penalties_saved":0,"penalties_missed":0,"yellow_cards":0,"red_cards":0,"saves":0,"bonus":0,"bps":0,"influence":"0.0","creativity":"0.0","threat":"0.0","ict_index":"0.0","value":45,"transfers_balance":-8087,"selected":85340,"transfers_in":644,"transfers_out":8731},{"element":61,"fixture":71,"opponent_team":1,"total_points":0,"was_home":false,"kickoff_time":"2019-10-06T13:00:00Z","team_h_score":1,"team_a_score":0,"round":8,"minutes":0,"goals_scored":0,"assists":0,"clean_sheets":0,"goals_conceded":0,"own_goals":0,"penalties_saved":0,"penalties_missed":0,"yellow_cards":0,"red_cards":0,"saves":0,"bonus":0,"bps":0,"influence":"0.0","creativity":"0.0","threat":"0.0","ict_index":"0.0","value":45,"transfers_balance":-8224,"selected":77220,"transfers_in":149,"transfers_out":8373},{"element":61,"fixture":82,"opponent_team":14,"total_points":0,"was_home":true,"kickoff_time":"2019-10-19T14:00:00Z","team_h_score":0,"team_a_score":0,"round":9,"minutes":0,"goals_scored":0,"assists":0,"clean_sheets":0,"goals_conceded":0,"own_goals":0,"penalties_saved":0,"penalties_missed":0,"yellow_cards":0,"red_cards":0,"saves":0,"bonus":0,"bps":0,"influence":"0.0","creativity":"0.0","threat":"0.0","ict_index":"0.0","value":44,"transfers_balance":-8237,"selected":69041,"transfers_in":28,"transfers_out":8265},{"element":61,"fixture":99,"opponent_team":18,"total_points":0,"was_home":false,"kickoff_time":"2019-10-26T14:00:00Z","team_h_score":0,"team_a_score":0,"round":10,"minutes":0,"goals_scored":0,"assists":0,"clean_sheets":0,"goals_conceded":0,"own_goals":0,"penalties_saved":0,"penalties_missed":0,"yellow_cards":0,"red_cards":0,"saves":0,"bonus":0,"bps":0,"influence":"0.0","creativity":"0.0","threat":"0.0","ict_index":"0.0","value":44,"transfers_balance":-1919,"selected":67675,"transfers_in":106,"transfers_out":2025},{"element":61,"fixture":103,"opponent_team":12,"total_points":0,"was_home":true,"kickoff_time":"2019-11-02T12:30:00Z","team_h_score":1,"team_a_score":0,"round":11,"minutes":0,"goals_scored":0,"assists":0,"clean_sheets":0,"goals_conceded":0,"own_goals":0,"penalties_saved":0,"penalties_missed":0,"yellow_cards":0,"red_cards":0,"saves":0,"bonus":0,"bps":0,"influence":"0.0","creativity":"0.0","threat":"0.0","ict_index":"0.0","value":44,"transfers_balance":-2435,"selected":65233,"transfers_in":99,"transfers_out":2534},{"element":61,"fixture":116,"opponent_team":13,"total_points":0,"was_home":false,"kickoff_time":"2019-11-09T15:00:00Z","team_h_score":2,"team_a_score":1,"round":12,"minutes":0,"goals_scored":0,"assists":0,"clean_sheets":0,"goals_conceded":0,"own_goals":0,"penalties_saved":0,"penalties_missed":0,"yellow_cards":0,"red_cards":0,"saves":0,"bonus":0,"bps":0,"influence":"0.0","creativity":"0.0","threat":"0.0","ict_index":"0.0","value":44,"transfers_balance":-2350,"selected":62941,"transfers_in":76,"transfers_out":2426},{"element":61,"fixture":123,"opponent_team":20,"total_points":0,"was_home":true,"kickoff_time":"2019-11-23T15:00:00Z","team_h_score":1,"team_a_score":2,"round":13,"minutes":0,"goals_scored":0,"assists":0,"clean_sheets":0,"goals_conceded":0,"own_goals":0,"penalties_saved":0,"penalties_missed":0,"yellow_cards":0,"red_cards":0,"saves":0,"bonus":0,"bps":0,"influence":"0.0","creativity":"0.0","threat":"0.0","ict_index":"0.0","value":43,"transfers_balance":-2199,"selected":60852,"transfers_in":145,"transfers_out":2344},{"element":61,"fixture":139,"opponent_team":17,"total_points":0,"was_home":false,"kickoff_time":"2019-11-30T15:00:00Z","team_h_score":3,"team_a_score":2,"round":14,"minutes":0,"goals_scored":0,"assists":0,"clean_sheets":0,"goals_conceded":0,"own_goals":0,"penalties_saved":0,"penalties_missed":0,"yellow_cards":0,"red_cards":0,"saves":0,"bonus":0,"bps":0,"influence":"0.0","creativity":"0.0","threat":"0.0","ict_index":"0.0","value":43,"transfers_balance":-1417,"selected":59555,"transfers_in":102,"transfers_out":1519},{"element":61,"fixture":148,"opponent_team":7,"total_points":2,"was_home":false,"kickoff_time":"2019-12-03T19:30:00Z","team_h_score":1,"team_a_score":0,"round":15,"minutes":90,"goals_scored":0,"assists":0,"clean_sheets":0,"goals_conceded":1,"own_goals":0,"penalties_saved":0,"penalties_missed":0,"yellow_cards":0,"red_cards":0,"saves":0,"bonus":0,"bps":12,"influence":"25.6","creativity":"1.4","threat":"21.0","ict_index":"4.8","value":43,"transfers_balance":-891,"selected":58764,"transfers_in":59,"transfers_out":950},{"element":61,"fixture":152,"opponent_team":10,"total_points":1,"was_home":true,"kickoff_time":"2019-12-07T15:00:00Z","team_h_score":0,"team_a_score":3,"round":16,"minutes":90,"goals_scored":0,"assists":0,"clean_sheets":0,"goals_conceded":3,"own_goals":0,"penalties_saved":0,"penalties_missed":0,"yellow_cards":0,"red_cards":0,"saves":0,"bonus":0,"bps":13,"influence":"16.6","creativity":"0.0","threat":"0.0","ict_index":"1.7","value":43,"transfers_balance":-751,"selected":58060,"transfers_in":158,"transfers_out":909},{"element":61,"fixture":163,"opponent_team":6,"total_points":6,"was_home":false,"kickoff_time":"2019-12-14T15:00:00Z","team_h_score":0,"team_a_score":1,"round":17,"minutes":90,"goals_scored":0,"assists":0,"clean_sheets":1,"goals_conceded":0,"own_goals":0,"penalties_saved":0,"penalties_missed":0,"yellow_cards":0,"red_cards":0,"saves":0,"bonus":0,"bps":24,"influence":"28.6","creativity":"0.3","threat":"27.0","ict_index":"5.6","value":43,"transfers_balance":-791,"selected":57333,"transfers_in":275,"transfers_out":1066},{"element":61,"fixture":172,"opponent_team":5,"total_points":2,"was_home":true,"kickoff_time":"2019-12-21T15:00:00Z","team_h_score":0,"team_a_score":1,"round":18,"minutes":90,"goals_scored":0,"assists":0,"clean_sheets":0,"goals_conceded":1,"own_goals":0,"penalties_saved":0,"penalties_missed":0,"yellow_cards":0,"red_cards":0,"saves":0,"bonus":0,"bps":16,"influence":"15.4","creativity":"0.1","threat":"8.0","ict_index":"2.4","value":43,"transfers_balance":3145,"selected":62026,"transfers_in":3877,"transfers_out":732},{"element":61,"fixture":182,"opponent_team":1,"total_points":1,"was_home":true,"kickoff_time":"2019-12-26T15:00:00Z","team_h_score":1,"team_a_score":1,"round":19,"minutes":90,"goals_scored":0,"assists":0,"clean_sheets":0,"goals_conceded":1,"own_goals":0,"penalties_saved":0,"penalties_missed":0,"yellow_cards":1,"red_cards":0,"saves":0,"bonus":0,"bps":10,"influence":"29.2","creativity":"0.7","threat":"4.0","ict_index":"3.4","value":43,"transfers_balance":293,"selected":61113,"transfers_in":1387,"transfers_out":1094},{"element":61,"fixture":192,"opponent_team":4,"total_points":1,"was_home":false,"kickoff_time":"2019-12-28T12:30:00Z","team_h_score":2,"team_a_score":0,"round":20,"minutes":90,"goals_scored":0,"assists":0,"clean_sheets":0,"goals_conceded":2,"own_goals":0,"penalties_saved":0,"penalties_missed":0,"yellow_cards":0,"red_cards":0,"saves":0,"bonus":0,"bps":19,"influence":"29.0","creativity":"10.7","threat":"4.0","ict_index":"4.4","value":43,"transfers_balance":114,"selected":61310,"transfers_in":992,"transfers_out":878},{"element":61,"fixture":210,"opponent_team":19,"total_points":0,"was_home":false,"kickoff_time":"2020-01-01T17:30:00Z","team_h_score":4,"team_a_score":0,"round":21,"minutes":90,"goals_scored":0,"assists":0,"clean_sheets":0,"goals_conceded":4,"own_goals":0,"penalties_saved":0,"penalties_missed":0,"yellow_cards":0,"red_cards":0,"saves":0,"bonus":0,"bps":14,"influence":"32.6","creativity":"0.8","threat":"0.0","ict_index":"3.3","value":43,"transfers_balance":9,"selected":61403,"transfers_in":1788,"transfers_out":1779},{"element":61,"fixture":212,"opponent_team":18,"total_points":0,"was_home":true,"kickoff_time":"2020-01-12T14:00:00Z","team_h_score":0,"team_a_score":3,"round":22,"minutes":0,"goals_scored":0,"assists":0,"clean_sheets":0,"goals_conceded":0,"own_goals":0,"penalties_saved":0,"penalties_missed":0,"yellow_cards":0,"red_cards":0,"saves":0,"bonus":0,"bps":0,"influence":"0.0","creativity":"0.0","threat":"0.0","ict_index":"0.0","value":43,"transfers_balance":-1322,"selected":60151,"transfers_in":1387,"transfers_out":2709},{"element":61,"fixture":227,"opponent_team":14,"total_points":0,"was_home":false,"kickoff_time":"2020-01-18T15:00:00Z","team_h_score":1,"team_a_score":0,"round":23,"minutes":0,"goals_scored":0,"assists":0,"clean_sheets":0,"goals_conceded":0,"own_goals":0,"penalties_saved":0,"penalties_missed":0,"yellow_cards":0,"red_cards":0,"saves":0,"bonus":0,"bps":0,"influence":"0.0","creativity":"0.0","threat":"0.0","ict_index":"0.0","value":43,"transfers_balance":-5623,"selected":54399,"transfers_in":9,"transfers_out":5632},{"element":61,"fixture":232,"opponent_team":4,"total_points":0,"was_home":true,"kickoff_time":"2020-01-21T19:30:00Z","team_h_score":3,"team_a_score":1,"round":24,"minutes":0,"goals_scored":0,"assists":0,"clean_sheets":0,"goals_conceded":0,"own_goals":0,"penalties_saved":0,"penalties_missed":0,"yellow_cards":0,"red_cards":0,"saves":0,"bonus":0,"bps":0,"influence":"0.0","creativity":"0.0","threat":"0.0","ict_index":"0.0","value":43,"transfers_balance":-2295,"selected":52100,"transfers_in":13,"transfers_out":2308},{"element":61,"fixture":241,"opponent_team":2,"total_points":0,"was_home":true,"kickoff_time":"2020-02-01T15:00:00Z","team_h_score":2,"team_a_score":1,"round":25,"minutes":0,"goals_scored":0,"assists":0,"clean_sheets":0,"goals_conceded":0,"own_goals":0,"penalties_saved":0,"penalties_missed":0,"yellow_cards":0,"red_cards":0,"saves":0,"bonus":0,"bps":0,"influence":"0.0","creativity":"0.0","threat":"0.0","ict_index":"0.0","value":43,"transfers_balance":-2026,"selected":50187,"transfers_in":8,"transfers_out":2034},{"element":61,"fixture":258,"opponent_team":15,"total_points":0,"was_home":false,"kickoff_time":"2020-02-09T14:00:00Z","team_h_score":2,"team_a_score":1,"round":26,"minutes":0,"goals_scored":0,"assists":0,"clean_sheets":0,"goals_conceded":0,"own_goals":0,"penalties_saved":0,"penalties_missed":0,"yellow_cards":0,"red_cards":0,"saves":0,"bonus":0,"bps":0,"influence":"0.0","creativity":"0.0","threat":"0.0","ict_index":"0.0","value":43,"transfers_balance":-1083,"selected":49176,"transfers_in":30,"transfers_out":1113},{"element":61,"fixture":262,"opponent_team":5,"total_points":0,"was_home":false,"kickoff_time":"2020-02-22T15:00:00Z","team_h_score":3,"team_a_score":0,"round":27,"minutes":0,"goals_scored":0,"assists":0,"clean_sheets":0,"goals_conceded":0,"own_goals":0,"penalties_saved":0,"penalties_missed":0,"yellow_cards":0,"red_cards":0,"saves":0,"bonus":0,"bps":0,"influence":"0.0","creativity":"0.0","threat":"0.0","ict_index":"0.0","value":43,"transfers_balance":-1023,"selected":48161,"transfers_in":10,"transfers_out":1033},{"element":61,"fixture":272,"opponent_team":6,"total_points":0,"was_home":true,"kickoff_time":"2020-02-29T15:00:00Z","team_h_score":2,"team_a_score":2,"round":28,"minutes":0,"goals_scored":0,"assists":0,"clean_sheets":0,"goals_conceded":0,"own_goals":0,"penalties_saved":0,"penalties_missed":0,"yellow_cards":0,"red_cards":0,"saves":0,"bonus":0,"bps":0,"influence":"0.0","creativity":"0.0","threat":"0.0","ict_index":"0.0","value":43,"transfers_balance":-693,"selected":47415,"transfers_in":10,"transfers_out":703},{"element":61,"fixture":286,"opponent_team":10,"total_points":0,"was_home":false,"kickoff_time":"2020-03-07T12:30:00Z","team_h_score":2,"team_a_score":1,"round":29,"minutes":0,"goals_scored":0,"assists":0,"clean_sheets":0,"goals_conceded":0,"own_goals":0,"penalties_saved":0,"penalties_missed":0,"yellow_cards":0,"red_cards":0,"saves":0,"bonus":0,"bps":0,"influence":"0.0","creativity":"0.0","threat":"0.0","ict_index":"0.0","value":43,"transfers_balance":-488,"selected":46965,"transfers_in":14,"transfers_out":502},{"element":61,"fixture":292,"opponent_team":7,"total_points":0,"was_home":true,"kickoff_time":"2020-06-20T18:45:00Z","team_h_score":0,"team_a_score":2,"round":39,"minutes":0,"goals_scored":0,"assists":0,"clean_sheets":0,"goals_conceded":0,"own_goals":0,"penalties_saved":0,"penalties_missed":0,"yellow_cards":0,"red_cards":0,"saves":0,"bonus":0,"bps":0,"influence":"0.0","creativity":"0.0","threat":"0.0","ict_index":"0.0","value":43,"transfers_balance":-402,"selected":46394,"transfers_in":335,"transfers_out":737},{"element":61,"fixture":310,"opponent_team":20,"total_points":0,"was_home":false,"kickoff_time":"2020-06-24T17:00:00Z","team_h_score":1,"team_a_score":0,"round":40,"minutes":0,"goals_scored":0,"assists":0,"clean_sheets":0,"goals_conceded":0,"own_goals":0,"penalties_saved":0,"penalties_missed":0,"yellow_cards":0,"red_cards":0,"saves":0,"bonus":0,"bps":0,"influence":"0.0","creativity":"0.0","threat":"0.0","ict_index":"0.0","value":43,"transfers_balance":-99,"selected":46355,"transfers_in":43,"transfers_out":142},{"element":61,"fixture":313,"opponent_team":13,"total_points":1,"was_home":true,"kickoff_time":"2020-07-01T17:00:00Z","team_h_score":1,"team_a_score":4,"round":41,"minutes":10,"goals_scored":0,"assists":0,"clean_sheets":0,"goals_conceded":0,"own_goals":0,"penalties_saved":0,"penalties_missed":0,"yellow_cards":0,"red_cards":0,"saves":0,"bonus":0,"bps":4,"influence":"8.2","creativity":"4.3","threat":"2.0","ict_index":"1.5","value":43,"transfers_balance":-113,"selected":46253,"transfers_in":21,"transfers_out":134},{"element":61,"fixture":325,"opponent_team":12,"total_points":0,"was_home":false,"kickoff_time":"2020-07-04T14:00:00Z","team_h_score":5,"team_a_score":2,"round":42,"minutes":0,"goals_scored":0,"assists":0,"clean_sheets":0,"goals_conceded":0,"own_goals":0,"penalties_saved":0,"penalties_missed":0,"yellow_cards":0,"red_cards":0,"saves":0,"bonus":0,"bps":0,"influence":"0.0","creativity":"0.0","threat":"0.0","ict_index":"0.0","value":43,"transfers_balance":-131,"selected":46148,"transfers_in":45,"transfers_out":176},{"element":61,"fixture":333,"opponent_team":17,"total_points":0,"was_home":true,"kickoff_time":"2020-07-09T17:00:00Z","team_h_score":0,"team_a_score":0,"round":43,"minutes":0,"goals_scored":0,"assists":0,"clean_sheets":0,"goals_conceded":0,"own_goals":0,"penalties_saved":0,"penalties_missed":0,"yellow_cards":0,"red_cards":0,"saves":0,"bonus":0,"bps":0,"influence":"0.0","creativity":"0.0","threat":"0.0","ict_index":"0.0","value":43,"transfers_balance":-221,"selected":45929,"transfers_in":6,"transfers_out":227},{"element":61,"fixture":342,"opponent_team":9,"total_points":0,"was_home":true,"kickoff_time":"2020-07-12T18:00:00Z","team_h_score":4,"team_a_score":1,"round":44,"minutes":0,"goals_scored":0,"assists":0,"clean_sheets":0,"goals_conceded":0,"own_goals":0,"penalties_saved":0,"penalties_missed":0,"yellow_cards":0,"red_cards":0,"saves":0,"bonus":0,"bps":0,"influence":"0.0","creativity":"0.0","threat":"0.0","ict_index":"0.0","value":43,"transfers_balance":-214,"selected":45715,"transfers_in":4,"transfers_out":218},{"element":61,"fixture":357,"opponent_team":11,"total_points":0,"was_home":false,"kickoff_time":"2020-07-15T17:00:00Z","team_h_score":2,"team_a_score":1,"round":45,"minutes":0,"goals_scored":0,"assists":0,"clean_sheets":0,"goals_conceded":0,"own_goals":0,"penalties_saved":0,"penalties_missed":0,"yellow_cards":0,"red_cards":0,"saves":0,"bonus":0,"bps":0,"influence":"0.0","creativity":"0.0","threat":"0.0","ict_index":"0.0","value":43,"transfers_balance":-156,"selected":45568,"transfers_in":4,"transfers_out":160},{"element":61,"fixture":362,"opponent_team":16,"total_points":0,"was_home":true,"kickoff_time":"2020-07-19T13:00:00Z","team_h_score":0,"team_a_score":2,"round":46,"minutes":0,"goals_scored":0,"assists":0,"clean_sheets":0,"goals_conceded":0,"own_goals":0,"penalties_saved":0,"penalties_missed":0,"yellow_cards":0,"red_cards":0,"saves":0,"bonus":0,"bps":0,"influence":"0.0","creativity":"0.0","threat":"0.0","ict_index":"0.0","value":43,"transfers_balance":-144,"selected":45425,"transfers_in":4,"transfers_out":148},{"element":61,"fixture":375,"opponent_team":8,"total_points":0,"was_home":false,"kickoff_time":"2020-07-26T15:00:00Z","team_h_score":1,"team_a_score":3,"round":47,"minutes":0,"goals_scored":0,"assists":0,"clean_sheets":0,"goals_conceded":0,"own_goals":0,"penalties_saved":0,"penalties_missed":0,"yellow_cards":0,"red_cards":0,"saves":0,"bonus":0,"bps":0,"influence":"0.0","creativity":"0.0","threat":"0.0","ict_index":"0.0","value":43,"transfers_balance":-238,"selected":45168,"transfers_in":13,"transfers_out":251}],"history_past":[{"season_name":"2018/19","element_code":223911,"start_cost":45,"end_cost":45,"total_points":27,"minutes":848,"goals_scored":0,"assists":1,"clean_sheets":2,"goals_conceded":17,"own_goals":0,"penalties_saved":0,"penalties_missed":0,"yellow_cards":1,"red_cards":0,"saves":0,"bonus":0,"bps":158,"influence":"177.2","creativity":"24.1","threat":"22.0","ict_index":"22.5"},{"season_name":"2019/20","element_code":223911,"start_cost":45,"end_cost":43,"total_points":27,"minutes":911,"goals_scored":1,"assists":0,"clean_sheets":1,"goals_conceded":19,"own_goals":0,"penalties_saved":0,"penalties_missed":0,"yellow_cards":1,"red_cards":0,"saves":0,"bonus":2,"bps":165,"influence":"276.8","creativity":"20.8","threat":"138.0","ict_index":"43.7"}]}